{"stat.craftItem.immersiveengineering.stone_decoration":54,"stat.mineBlock.libvulpes.placeholder":1,"stat.useItem.buildcraftfactory.tank":9,"stat.drop.mist.respirator_single":1,"stat.craftItem.embers.stamp_bar":2,"stat.mineBlock.rftools.remote_storage":2,"stat.drop.minecraft.gunpowder":6,"stat.useItem.primal.suet":8,"stat.craftItem.primal.torch_wood":378,"stat.pickup.buildcrafttransport.pipe_diamond_item":6,"stat.mineBlock.refinedstorage.exporter":1,"stat.craftItem.environmentaltech.diode":2,"stat.craftItem.embers.bin":6,"stat.pickup.magneticraft.connector":90,"stat.pickup.minecraft.rotten_flesh":342,"stat.drop.immersivepetroleum.schematic":1,"stat.pickup.earthworks.item_dirt":35,"stat.craftItem.redstonearsenal.material":8,"stat.pickup.botania.quartz":6,"stat.useItem.botania.flower":5,"stat.pickup.rftools.modular_storage":2,"stat.mineBlock.xnet.controller":2,"stat.drop.flexibletools.tool_upgrade_support":4,"stat.craftItem.minecraft.iron_shovel":3,"stat.mineBlock.forestry.humus":2,"stat.craftItem.fp.scrench":5,"stat.pickup.primal.urushi_ground":54,"stat.craftItem.bibliocraft.shelf":1,"stat.craftItem.forestry.sturdy_machine":6,"stat.craftItem.advancedrocketry.chemicalreactor":1,"stat.craftItem.roots.runestone_brick":12,"stat.pickup.minecraft.stained_hardened_clay":494,"stat.useItem.environmentaltech.solar_cont_1":1,"stat.pickup.minecraft.double_plant":50,"stat.craftItem.minecraft.glass_pane":255,"stat.craftItem.embers.block_caminite_brick_slab":8,"stat.useItem.minecraft.hardened_clay":3,"stat.useItem.advancedrocketry.loader":5,"stat.furnaceInteraction":309,"stat.mineBlock.libvulpes.forgepowerinput":2,"stat.pickup.xnet.router":2,"stat.pickup.environmentaltech.solar_cell_kyronite":25,"stat.pickup.extendedcrafting.table_elite":2,"stat.pickup.mist.sponge_spore":10,"stat.drop.minecraft.cactus":23,"stat.pickup.biomesoplenty.stone_formations":9,"stat.craftItem.environmentaltech.litherite_crystal":72,"stat.mineBlock.appliedenergistics2.charger":6,"stat.pickup.primal.ladder_oak":3,"stat.pickup.fp.industrie_ofen":19,"stat.craftItem.botania.pool":4,"stat.useItem.minecraft.flint_and_steel":82,"stat.craftItem.embers.plate_caminite":8,"stat.useItem.minecraft.wheat_seeds":193,"stat.mineBlock.fp.spacedoor":27,"stat.pickup.immersiveengineering.sheetmetal":9,"stat.pickup.minecraft.emerald":31,"stat.pickup.primal.bear_meat_raw":7,"stat.craftItem.primal.brickform":5,"stat.pickup.minecraft.egg":1295,"stat.pickup.foundry.moldstation":1,"stat.craftItem.flexibletools.picki":4,"stat.pickup.thermalexpansion.tank":131,"stat.pickup.xlfoodmod.raw_corn":79,"stat.pickup.buildcrafttransport.pipe_wood_power":23,"stat.pickup.minecraft.sea_lantern":13,"stat.useItem.survivalist.jerky":69,"stat.drop.minecraft.iron_ingot":66,"stat.craftItem.minecraft.cooked_mutton":5,"stat.pickup.waterstrainer.net":1,"stat.pickup.fp.brennstoff_generator":4,"stat.chestOpened":9088,"stat.pickup.fp.color_plasma_on":13,"stat.drop.xlfoodmod.fried_egg":3,"stat.craftItem.magneticraft.copper_tank":2,"stat.craftItem.embers.ashen_stone":24,"stat.drop.primal.flint_knapp":12,"stat.killEntity.Vex":1,"stat.useItem.chisel.stonebrick":81,"stat.craftItem.minecraft.coal":18,"stat.pickup.primal.brickform":23,"stat.pickup.magneticraft.crushing_table":1,"stat.pickup.minecraft.carrot":4,"stat.drop.minecraft.stone_sword":1,"stat.craftItem.magneticraft.iron_pipe":48,"stat.useItem.immcraft.chest":4,"stat.craftItem.foundry.componentblock":15,"stat.craftItem.xlfoodmod.cooked_dough":30,"stat.drop.roots.firestarter":1,"stat.drop.minecraft.double_plant":11,"stat.pickup.fp.menelaus_mushroom":3,"stat.pickup.rftools.screen_controller":1,"stat.pickup.xlfoodmod.tomato":405,"stat.pickup.environmentaltech.modifier_speed":12,"stat.pickup.immersiveengineering.stone_decoration":150,"stat.pickup.minecraft.dye":109,"stat.pickup.minecraft.planks":1618,"stat.mineBlock.fp.opti_bench":3,"stat.craftItem.primal.drain_scoria":4,"stat.pickup.biomesoplenty.waterlily":2,"stat.pickup.thermaldynamics.duct_16":37,"stat.pickup.actuallyadditions.block_display_stand":4,"stat.killEntity.FP-EvilRobot":9,"stat.pickup.biomesoplenty.persimmon":24,"stat.pickup.exnihilocreatio.item_mesh":41,"stat.drop.minecraft.rotten_flesh":38,"stat.pickup.openblocks.tank":14,"stat.craftItem.primal.barrel":14,"stat.pickup.minecraft.magma":111,"stat.craftItem.primal.ciniscotta_brick":35,"stat.drop.forestry.loam":6,"stat.useItem.actuallyadditions.item_canola_seed":1,"stat.pickup.embers.beam_cannon":2,"stat.pickup.woot.cell":1,"stat.craftItem.flexibletools.shovi":4,"stat.mineBlock.biomesoplenty.sapling_0":61,"stat.pickup.minecraft.tipped_arrow":30,"stat.useItem.modularmachinery.blockinputbus":2,"stat.mineBlock.primal.brickform":23,"stat.mineBlock.actuallyadditions.block_atomic_reconstructor":3,"stat.pickup.refinedstorage.storage_disk":1,"stat.pickup.mist.respirator_single":1,"stat.craftItem.refinedstorage.storage_disk":1,"stat.craftItem.minecraft.dirt":967,"stat.craftItem.minecraft.wooden_door":3,"stat.craftItem.magneticraft.ingots":39,"stat.useItem.biomesoplenty.dirt":1,"stat.pickup.minecraft.iron_door":6,"stat.mineBlock.magneticraft.sluice_box":7,"stat.craftItem.minecraft.cobblestone":130,"stat.pickup.storagedrawers.controller":3,"stat.mineBlock.minecraft.cobblestone":109,"stat.pickup.minecraft.flint":569,"stat.craftItem.embers.plate_caminite_raw":16,"stat.mineBlock.foundry.burnerheater":2,"stat.pickup.minecraft.flower_pot":3,"stat.mineBlock.foundry.moldstation":1,"stat.pickup.botania.alchemycatalyst":11,"stat.pickup.terraqueous.sapling":1,"stat.pickup.fp.sword_retium":2,"stat.mineBlock.embers.ember_emitter":3,"stat.craftItem.immersiveengineering.conveyor":4,"stat.mineBlock.botania.runealtar":4,"stat.useItem.thermaldynamics.duct_16":38,"stat.mineBlock.minecraft.dropper":4,"stat.pickup.astralsorcery.blockattunementrelay":3,"stat.pickup.forge.bucketfilled":20,"stat.craftItem.advancedrocketry.satellite":1,"stat.pickup.actuallyadditions.item_pants_crystal_green":5,"stat.mineBlock.magneticraft.crushing_table":1,"stat.craftItem.minecraft.lapis_block":2,"stat.pickup.earthworks.block_chalk":7,"stat.craftItem.environmentaltech.photovoltaic_cell":41,"stat.pickup.fp.neon_bricks":77,"stat.useItem.libvulpes.hatch":1,"stat.mineBlock.fp.fuelcell":1,"stat.useItem.botania.livingwood":20,"stat.pickup.roots.bonfire":2,"stat.useItem.thermaldynamics.duct_32":103,"stat.useItem.minecraft.wooden_slab":1,"stat.pickup.fp.spacedoor":27,"stat.useItem.magneticraft.multiblock_parts":54,"stat.pickup.thermalexpansion.dynamo":3,"stat.craftItem.embers.brick_caminite":165,"stat.pickup.actuallyadditions.block_crystal":19,"stat.pickup.astralsorcery.itemskyresonator":1,"stat.drop.skyresources.casing":1,"stat.pickup.xlfoodmod.cucumber_seeds":3,"stat.pickup.immcraft.furnace":3,"stat.drop.minecraft.flint_and_steel":1,"stat.mineBlock.immcraft.furnace":2,"stat.pickup.buildcraftsilicon.redstone_chipset":29,"stat.pickup.industrialforegoing.adult_filter":1,"stat.pickup.storagedrawers.compdrawers":3,"stat.craftItem.storagedrawers.upgrade_void":4,"stat.pickup.thermalexpansion.frame":13,"stat.pickup.primal.lever_wood":6,"stat.pickup.thermaldynamics.duct_32":38,"stat.killEntity.Squid":12,"stat.pickup.embers.ember_activator":2,"stat.sprintOneCm":16067908,"stat.useItem.mist.cobblestone":47,"stat.useItem.magneticraft.battery":1,"stat.mineBlock.embers.beam_cannon":2,"stat.pickup.waterstrainer.efficiency_meter":1,"stat.pickup.minecraft.leather_leggings":4,"stat.useItem.primal.flint_hoe":57,"stat.useItem.fp.itemfood":1,"stat.pickup.advancedrocketry.satellite":1,"stat.mineBlock.environmentaltech.solar_cont_1":1,"stat.killEntity.Zombie":44,"stat.craftItem.storagedrawers.compdrawers":10,"stat.pickup.environmentaltech.kyronite_crystal":382,"stat.mineBlock.immersiveengineering.stone_device":3,"stat.pickup.minecraft.obsidian":188,"stat.mineBlock.botania.spreader":8,"stat.pickup.primal.bark_oak":35,"stat.craftItem.magneticraft.crafting":13,"stat.mineBlock.refinedstorage.solderer":4,"stat.craftItem.fp.grenade":14,"stat.pickup.extendedcrafting.table_basic":6,"stat.pickup.buildcraftsilicon.assembly_table":6,"stat.pickup.immcraft.rock":39,"stat.pickup.minecraft.coal":2621,"stat.craftItem.refinedstorage.external_storage":1,"stat.pickup.minecraft.dirt":948,"stat.useItem.astralsorcery.blockblackmarble":43,"stat.craftItem.libvulpes.forgepowerinput":5,"stat.craftItem.modularmachinery.blockcontroller":2,"stat.craftItem.advancedrocketry.monitoringstation":1,"stat.drop.ceramics.unfired_clay":1,"stat.drop.minecraft.enchanting_table":1,"stat.drop.tconstruct.clear_glass":2,"stat.pickup.primal.plant_fiber":989,"stat.pickup.immersiveengineering.powerpack":1,"stat.pickup.minecraft.magma_cream":1,"stat.craftItem.minecraft.glowstone":3,"stat.pickup.botania.spreader":12,"stat.mineBlock.exnihilocreatio.block_axle_stone":10,"stat.useItem.primal.flint_shovel":320,"stat.craftItem.primal.terraclay_clump":4,"stat.pickup.fp.erze":164,"stat.drop.minecraft.wheat":5,"stat.killEntity.primal:canis_campestris":3,"stat.pickup.forestry.phosphor":1574,"stat.pickup.minecraft.rabbit_foot":1,"stat.pickup.tconstruct.clear_glass":88,"stat.pickup.genetics.lab_machine":1,"stat.drop.minecraft.egg":22,"stat.mineBlock.refinedstorage.cable":8,"stat.craftItem.fp.erz_blocke":140,"stat.useItem.minecraft.redstone_ore":27,"stat.pickup.minecraft.cooked_beef":47,"stat.mineBlock.forestry.loam":173,"stat.craftItem.primal.thin_slab_oak":2,"stat.pickup.biomesoplenty.gem":647,"stat.pickup.electrostatics.resin":52,"stat.drop.botania.lexicon":2,"stat.useItem.advancedrocketry.fueltank":9,"stat.useItem.embers.item_pipe":159,"stat.pickup.minecraft.beetroot_seeds":7,"stat.craftItem.refinedstorage.controller":1,"stat.drop.exnihilocreatio.item_mesh":4,"stat.mineBlock.forestry.moistener":3,"stat.pickup.astralsorcery.blockmarble":2352,"stat.mineBlock.compactmachines3.fieldprojector":13,"stat.useItem.botania.livingwoodbow":35,"stat.useItem.minecraft.bookshelf":43,"stat.mineBlock.skyresources.lifeinfuser":1,"stat.pickup.mist.sponge":1,"stat.mineBlock.chisel.glowstone":1,"stat.craftItem.libvulpes.battery":9,"stat.craftItem.primal.diamond_pickaxe":6,"stat.pickup.primal.adobebrick_mix":1,"stat.killEntity.Blaze":6,"stat.mineBlock.embers.item_pump":50,"stat.craftItem.forestry.frame_untreated":4,"stat.pickup.environmentaltech.solar_cont_1":5,"stat.pickup.actuallyadditions.item_chest_crystal_green":8,"stat.pickup.environmentaltech.solar_cont_2":4,"stat.useItem.forestry.honeyed_slice":3,"stat.mineBlock.embers.dawnstone_anvil":3,"stat.useItem.flexibletools.multi":4409,"stat.pickup.botania.pavement":46,"stat.mineBlock.minecraft.sand":66,"stat.drop.tconstruct.lumberaxe":1,"stat.mineBlock.environmentaltech.void_ore_miner_cont_1":3,"stat.mineBlock.environmentaltech.void_ore_miner_cont_2":2,"stat.mineBlock.advancedrocketry.rocketbuilder":1,"stat.pickup.fp.stone":69,"stat.pickup.biomesoplenty.mud":64,"stat.pickup.astralsorcery.itemjournal":1,"stat.craftItem.minecraft.magma_cream":2,"stat.mineBlock.magneticraft.solar_mirror":1,"stat.drop.exnihilocreatio.item_material":1,"stat.pickup.environmentaltech.laser_lens":8,"stat.craftItem.storagedrawers.upgrade_template":16,"stat.pickup.roots.moonglow_leaf":67,"stat.pickup.minecraft.wooden_button":2,"stat.useItem.fp.cristall":37,"stat.pickup.botania.spark":6,"stat.pickup.primal.adobebrick_dry":73,"stat.mineBlock.primal.cauldron":2,"stat.drop.primal.flint_shears":1,"stat.useItem.earthworks.block_wattle":44,"stat.mineBlock.buildcraftfactory.pump":3,"stat.drop.minecraft.pumpkin_seeds":13,"stat.useItem.tconstruct.scythe":3873,"stat.drop.earthworks.item_sand":2,"stat.pickup.primal.blue_stone":43,"stat.craftItem.extendedcrafting.table_basic":2,"stat.craftItem.advancedrocketry.misc":19,"stat.drop.biomesoplenty.leaves_0":9,"stat.drop.biomesoplenty.leaves_1":3,"stat.pickup.advancedrocketry.loader":4,"stat.craftItem.immersiveengineering.material":137,"stat.useItem.botania.hourglass":1,"stat.craftItem.actuallyadditions.item_chest_crystal_green":4,"stat.pickup.biomesoplenty.dried_sand":9,"stat.pickup.ironchest.iron_chest":73,"stat.useItem.transprot.dispatcher":1,"stat.pickup.fp.erse":183,"stat.useItem.jaff.fish_bucket_cod":1,"stat.useItem.embers.item_transfer":3,"stat.drop.openblocks.sleeping_bag":1,"stat.craftItem.skyresources.fluiddropper":2,"stat.craftItem.embers.pipe":24,"stat.pickup.appliedenergistics2.grindstone":1,"stat.craftItem.mist.sponge_fibre_clear":9,"stat.pickup.minecraft.waterlily":7,"stat.pickup.embers.stairs_ashen_brick":2,"stat.craftItem.immcraft.furnace":4,"stat.craftItem.environmentaltech.modifier_null":8,"stat.useItem.chisel.stonebrick2":21,"stat.useItem.environmentaltech.modifier_null":5,"stat.pickup.embers.pump":38,"stat.pickup.skyresources.rockcrusher":3,"stat.drop.minecraft.stone":4,"stat.useItem.primal.flint_axe":337,"stat.pickup.minecraft.melon_seeds":2,"stat.pickup.minecraft.dropper":4,"stat.useItem.embers.tinker_hammer":58,"stat.craftItem.primal.flint_shears":3,"stat.useItem.earthworks.block_concrete":68,"stat.craftItem.modularmachinery.blockoutputbus":2,"stat.pickup.minecraft.heavy_weighted_pressure_plate":1,"stat.pickup.primal.rush_stems":227,"stat.craftItem.advancedrocketry.satelliteprimaryfunction":8,"stat.craftItem.botania.teruterubozu":2,"stat.craftItem.waterstrainer.strainer_survivalist_dense_reinforced":8,"stat.craftItem.biomesoplenty.terrestrial_artifact":4,"stat.mineBlock.minecraft.gravel":3,"stat.useItem.minecraft.wool":1,"stat.craftItem.primal.tall_grass_seeds":4,"stat.pickup.immersivepetroleum.material":257,"stat.craftItem.embers.item_pump":32,"stat.pickup.minecraft.flint_and_steel":1,"stat.pickup.magneticraft.light_plates":4,"stat.pickup.minecraft.iron_nugget":13,"stat.craftItem.fp.partpress":1,"stat.craftItem.minecraft.redstone_block":6,"stat.pickup.minecraft.crafting_table":5,"stat.drop.minecraft.tallgrass":7,"stat.pickup.buildcrafttransport.pipe_cobble_power":80,"stat.pickup.primal.flint_axe":1,"stat.pickup.chisel.basalt":22,"stat.pickup.minecraft.redstone_block":1,"stat.craftItem.environmentaltech.solar_cell_litherite":18,"stat.craftItem.botania.dreamwood":16,"stat.craftItem.environmentaltech.laser_lens":2,"stat.pickup.astralsorcery.blockaltar":8,"stat.pickup.immcraft.chest":24,"stat.pickup.soot.ember_grit":1,"stat.craftItem.minecraft.stone_button":64,"stat.useItem.biomesoplenty.persimmon":20,"stat.mineBlock.fp.industrie_ofen":19,"stat.craftItem.sparkshammers.hammer_craft":2,"stat.pickup.teslathingies.compound_maker":3,"stat.pickup.primal.rush_tips":256,"stat.craftItem.mist.niobium_pickaxe":3,"stat.craftItem.skyresources.combustionheater":2,"stat.drop.immersiveengineering.material":2,"stat.useItem.exnihilocreatio.block_crucible":19,"stat.pickup.roots.aubergine_item":51,"stat.pickup.skyresources.crucibleinserter":7,"stat.pickup.oreberries.lead_oreberry":2,"stat.useItem.embers.ember_receiver":5,"stat.pickup.exnihilocreatio.item_ore_cobalt":310,"stat.pickup.exnihilocreatio.block_axle_stone":9,"stat.craftItem.embers.ember_receiver":8,"stat.drop.minecraft.bucket":4,"stat.useItem.minecraft.baked_potato":387,"stat.pickup.minecraft.golden_rail":4,"stat.pickup.chisel.technicalnew":85,"stat.mineBlock.minecraft.brown_mushroom":2,"stat.useItem.xlfoodmod.fried_egg":227,"stat.useItem.fp.neon_sand":17,"stat.craftItem.foundry.machine":9,"stat.craftItem.tconstruct.slimesling":4,"stat.climbOneCm":574710,"stat.pickup.buildcraftsilicon.advanced_crafting_table":6,"stat.craftItem.appliedenergistics2.crank":3,"stat.craftItem.naturescompass.naturescompass":2,"stat.pickup.thermalexpansion.machine":15,"stat.drop.minecraft.quartz":7,"stat.useItem.primal.flint_hatchet":31,"stat.craftItem.immersiveengineering.wooden_decoration":12,"stat.drop.oreberries.iron_oreberry":1,"stat.useItem.tconstruct.lumberaxe":1661,"stat.drop.immersiveengineering.metal":43,"stat.drop.botania.alchemycatalyst":8,"stat.craftItem.minecraft.stone_pickaxe":2,"stat.craftItem.buildcrafttransport.pipe_clay_item":8,"stat.pickup.minecraft.cobblestone":768,"stat.drop.rftools.storage_module_tablet":7,"stat.mineBlock.buildcraftcore.engine":62,"stat.pickup.thermalfoundation.armor.plate_lead":2,"stat.drop.fp.scrench":1,"stat.mineBlock.embers.stamper":4,"stat.craftItem.forestry.wood_pile":227,"stat.pickup.buildcraftsilicon.laser":29,"stat.pickup.actuallyadditions.item_rice_seed":4,"stat.useItem.fp.spacedoor":15,"stat.drop.minecraft.coal":38,"stat.craftItem.primal.iron_strand":1152,"stat.craftItem.fp.recycler":1,"stat.pickup.survivalist.rack":2,"stat.craftItem.embers.blend_caminite":28,"stat.pickup.embers.isolated_materia":29,"stat.craftItem.mist.respirator_single":6,"stat.drop.minecraft.dirt":9,"stat.pickup.minecraft.iron_shovel":2,"stat.pickup.minecraft.trapdoor":1,"stat.craftItem.tconstruct.slime_boots":2,"stat.pickup.botania.petal":6,"stat.useItem.primal.flint_workblade":79,"stat.killEntity.ancient_golem":13,"stat.drop.roots.ritual_book":1,"stat.useItem.botania.lexicon":2,"stat.pickup.primal.magnetite_dust":1,"stat.craftItem.botania.vial":3,"stat.craftItem.botany.misc":140,"stat.pickup.botania.magnetring":1,"stat.useItem.astralsorcery.itemexchangewand":9,"stat.pickup.botania.flower":44,"stat.mineBlock.magneticraft.conveyor_belt":5,"stat.mineBlock.minecraft.planks":6,"stat.pickup.foundry.machine":46,"stat.pickup.fp.color_iron":1141,"stat.pickup.chisel.hardenedclay1":1,"stat.craftItem.minecraft.piston":40,"stat.pickup.roots.wood_hammer":1,"stat.pickup.refinedstorage.importer":2,"stat.craftItem.buildcrafttransport.pipe_iron_item":40,"stat.mineBlock.roots.thatch":1,"stat.craftItem.biomesoplenty.ash_block":8616,"stat.drop.tconstruct.channel":1,"stat.killEntity.deer":1,"stat.useItem.minecraft.apple":96,"stat.drop.embers.alchemic_waste":1,"stat.useItem.immcraft.rock":9,"stat.useItem.minecraft.carpet":4,"stat.mineBlock.rftools.screen":2,"stat.craftItem.primal.diamond_shovel":4,"stat.pickup.minecraft.fence":205,"stat.craftItem.embers.vacuum":5,"stat.mineBlock.embers.breaker":79,"stat.useItem.minecraft.stone_axe":247,"stat.pickup.forestry.thermionic_tubes":4,"stat.useItem.tconstruct.metal":9,"stat.pickup.actuallyadditions.block_misc":3,"stat.pickup.embers.dawnstone_anvil":3,"stat.pickup.magneticraft.battery_item_medium":2,"stat.pickup.astralsorcery.itemusabledust":16,"stat.mineBlock.immcraft.rock":21,"stat.pickup.actuallyadditions.item_coffee_seed":2,"stat.pickup.buildcraftcore.fragile_fluid_shard":48,"stat.mineBlock.tconstruct.tooltables":10,"stat.pickup.primal.obsidian_shard":15,"stat.pickup.xlfoodmod.tomato_seeds":356,"stat.useItem.jaff.fish_bucket_pufferfish":1,"stat.mineBlock.botany.soil":6,"stat.pickup.minecraft.prismarine_shard":203,"stat.drop.minecraft.water_bucket":1,"stat.craftItem.botania.manatablet":2,"stat.drop.primal.obsidian_plate":4,"stat.useItem.xlfoodmod.kebab":3,"stat.useItem.xlfoodmod.lettuce":4,"stat.damageDealt":99684,"stat.useItem.magneticraft.connector":94,"stat.craftItem.minecraft.anvil":2,"stat.pickup.actuallyadditions.item_canola_seed":3,"stat.craftItem.skyresources.sandstoneinfusionstone":10,"stat.useItem.minecraft.crafting_table":1,"stat.craftItem.minecraft.gravel":532,"stat.useItem.compactmachines3.fieldprojector":6,"stat.pickup.ceramics.clay_bucket":25,"stat.craftItem.exnihilocreatio.item_material":175,"stat.pickup.thermalfoundation.armor.boots_lead":3,"stat.pickup.forestry.loam":199,"stat.mineBlock.persistentbits.chunk_loader":1,"stat.craftItem.immcraft.chest":19,"stat.drop.advancedrocketry.satellite":2,"stat.craftItem.openblocks.elevator":8,"stat.pickup.chisel.offsettool":1,"stat.drop.modularmachinery.itemblueprint":1,"stat.pickup.botany.soil":6,"stat.craftItem.fp.composite_door":3,"stat.pickup.biomesoplenty.mudball":326,"stat.pickup.fp.sand":16,"stat.craftItem.minecraft.redstone":72,"stat.craftItem.magneticraft.sluice_box":1,"stat.useItem.buildcrafttransport.pipe_quartz_power":35,"stat.useItem.minecraft.cactus":49,"stat.drop.forestry.apatite":29,"stat.mineBlock.foundry.castingtable":25,"stat.mineBlock.immcraft.in_world_placer":1,"stat.killEntity.Chicken":17,"stat.craftItem.forestry.squeezer":2,"stat.craftItem.minecraft.fence":135,"stat.craftItem.xlfoodmod.taco_salad":2,"stat.craftItem.foundry.fluidcontainer":12,"stat.craftItem.embers.block_dawnstone":8,"stat.drop.biomesoplenty.mud":2,"stat.pickup.industrialforegoing.mob_slaughter_factory":1,"stat.pickup.fp.color_glas":1,"stat.mineBlock.advancedrocketry.satellitecontrolcenter":1,"stat.pickup.minecraft.wooden_slab":3,"stat.pickup.terraqueous.flowers_single":9,"stat.leaveGame":146,"stat.pickup.survivalist.sawmill":1,"stat.useItem.exnihilocreatio.block_waterwheel":14,"stat.useItem.minecraft.glowstone":10,"stat.craftItem.minecraft.string":254,"stat.pickup.environmentaltech.solar_cell_erodium":29,"stat.pickup.waterstrainer.strainer_base":26,"stat.craftItem.botany.trowel_wood":2,"stat.craftItem.environmentaltech.laser_lens_colored":1,"stat.mineBlock.embers.pump":42,"stat.craftItem.mist.niobium_ingot":38,"stat.pickup.fp.color_luftung":24,"stat.useItem.exnihilocreatio.block_sieve":35,"stat.mineBlock.rftools.storage_terminal":1,"stat.drop.rftools.powercell_advanced":1,"stat.pickup.chisel.chisel_iron":2,"stat.pickup.xlfoodmod.strawberry_seeds":10,"stat.pickup.xlfoodmod.lettuce":184,"stat.useItem.botany.soil":3,"stat.useItem.primal.barrel":7,"stat.useItem.minecraft.iron_shovel":250,"stat.pickup.buildcrafttransport.pipe_diamond_wood_fluid":1,"stat.pickup.survivalist.chopping_block":5,"stat.drop.terraqueous.foliage1":8,"stat.mineBlock.minecraft.hopper":71,"stat.pickup.industrialforegoing.pink_slime":1,"stat.mineBlock.botania.flower":3,"stat.drop.terraqueous.foliage3":1,"stat.drop.minecraft.red_flower":66,"stat.pickup.mist.sand":68,"stat.craftItem.primal.flint_workblade":2,"stat.pickup.botania.livingwood":49,"stat.mineBlock.fp.extern_cooler":57,"stat.pickup.biomesoplenty.flower_0":1,"stat.useItem.minecraft.stained_glass":2,"stat.drop.botania.dreamwood":1,"stat.craftItem.botany.trowel_diamond":2,"stat.pickup.magneticraft.multiblock_parts":109,"stat.craftItem.thermalfoundation.armor.legs_lead":3,"stat.mineBlock.rftools.storage_scanner":2,"stat.craftItem.primal.hardened_stone":19,"stat.drop.immersiveengineering.blueprint":1,"stat.pickup.roots.straw":96,"stat.mineBlock.skyresources.crucibleinserter":7,"stat.craftItem.waterstrainer.strainer_survivalist_solid":22,"stat.mineBlock.primal.scoria_stone":3,"stat.pickup.environmentaltech.litherite_crystal":220,"stat.drop.minecraft.torch":2,"stat.mineBlock.fp.flash_server":84,"stat.killEntity.thermalfoundation.blitz":44,"stat.mineBlock.fp.assembly_table":2,"stat.useItem.earthworks.block_wood_shingle":67,"stat.craftItem.advancedrocketry.satelliteidchip":7,"stat.useItem.minecraft.stone":133,"stat.pickup.minecraft.arrow":66,"stat.pickup.oreberries.tin_oreberry":3,"stat.drop.flexibletools.multi":7,"stat.craftItem.primal.flint_axe":8,"stat.mineBlock.industrialforegoing.crop_sower":2,"stat.useItem.embers.ashen_brick_slab":31,"stat.craftItem.skyresources.heat":2,"stat.mineBlock.minecraft.concrete_powder":2,"stat.drop.immcraft.furnace":2,"stat.pickup.fp.research_blueprint":1,"stat.pickup.astralsorcery.blockstarlightinfuser":1,"stat.useItem.primal.torch_wood":23,"stat.pickup.forestry.ffarm":38,"stat.mineBlock.fp.neon_sand":3,"stat.craftItem.rftools.storage_module_tablet":1,"stat.mineBlock.botania.altgrass":286,"stat.mineBlock.yabba.item_barrel":9,"stat.mineBlock.minecraft.dirt":219,"stat.pickup.embers.breaker":79,"stat.pickup.embers.alchemic_waste":1,"stat.pickup.fp.extern_cooler":57,"stat.pickup.immersiveengineering.seed":887,"stat.useItem.minecraft.bread":1,"stat.pickup.terraqueous.foliage1":22,"stat.pickup.fp.escenner":3,"stat.pickup.terraqueous.foliage3":1,"stat.craftItem.flexibletools.axi":4,"stat.useItem.minecraft.gravel":1,"stat.mineBlock.minecraft.double_plant":8,"stat.pickup.environmentaltech.modifier_null":36,"stat.drop.embers.vacuum":1,"stat.useItem.exnihilocreatio.block_axle_stone":11,"stat.craftItem.immersiveengineering.tool":2,"stat.useItem.astralsorcery.itemarchitectwand":9,"stat.pickup.forestry.ash":389,"stat.craftItem.waterstrainer.strainer_base":8,"stat.pickup.embers.ingot_dawnstone":156,"stat.useItem.botania.livingrock0wall":4,"stat.craftItem.primal.slat_iron":6,"stat.pickup.primal.cauldron_slag":5,"stat.mineBlock.minecraft.log":2139,"stat.craftItem.xlfoodmod.fried_egg":72,"stat.pickup.buildcrafttransport.pipe_cobble_fluid":1,"stat.craftItem.botania.pylon":3,"stat.pickup.embers.ancient_motive_core":10,"stat.pickup.biomesoplenty.dirt":14,"stat.mineBlock.exnihilocreatio.block_crucible":13,"stat.craftItem.thermalexpansion.frame":10,"stat.pickup.minecraft.wool":241,"stat.drop.flexibletools.tool_upgrade_effect":1,"stat.craftItem.magneticraft.connector":23,"stat.cakeSlicesEaten":55,"stat.pickup.embers.mech_core":5,"stat.mineBlock.skyresources.crucible":6,"stat.craftItem.storagedrawers.basicdrawers":32,"stat.pickup.roots.pereskia_blossom":71,"stat.pickup.primal.desiccated_stone":323,"stat.craftItem.advancedrocketry.satellitepowersource":3,"stat.drop.woot.upgrade":3,"stat.drop.thermalfoundation.material":119,"stat.craftItem.minecraft.wool":8,"stat.craftItem.primal.flint_saw":1,"stat.useItem.minecraft.snow":27,"stat.useItem.waystones.waystone":2,"stat.useItem.minecraft.obsidian":4,"stat.mineBlock.ironchest.iron_chest":78,"stat.pickup.refinedstorage.grid":3,"stat.pickup.minecraft.bow":1,"stat.pickup.actuallyadditions.block_empowerer":1,"stat.mineBlock.survivalist.sawmill":1,"stat.useItem.xlfoodmod.corn_seeds":3,"stat.useItem.tconstruct.clear_glass":25,"stat.useItem.primal.drain_scoria":2,"stat.pickup.fp.modul_2":3,"stat.pickup.actuallyadditions.item_booklet":1,"stat.pickup.industrialforegoing.crop_recolector":1,"stat.pickup.fp.color_iron_step_half_0":18,"stat.mineBlock.embers.bin":4,"stat.drop.tombmanygraves.death_list":1,"stat.craftItem.botania.dye":1,"stat.timeSinceDeath":7312380,"stat.craftItem.buildcraftsilicon.laser":5,"stat.craftItem.immersiveengineering.treated_wood":51,"stat.mineBlock.botania.livingwood":17,"stat.craftItem.foundry.refractoryhopper":2,"stat.drop.minecraft.blaze_powder":1,"stat.craftItem.embers.breaker":2,"stat.pickup.minecraft.nether_wart":1,"stat.drop.tconstruct.throwball":9,"stat.mineBlock.minecraft.enchanting_table":1,"stat.pickup.fp.composite_helmet":2,"stat.drop.astralsorcery.itemrockcrystalsimple":40,"stat.craftItem.earthworks.item_chalk":16,"stat.craftItem.minecraft.stone_hoe":2,"stat.pickup.botania.manaresource":212,"stat.craftItem.thermalfoundation.armor.helmet_lead":2,"stat.useItem.buildcrafttransport.pipe_cobble_power":64,"stat.mineBlock.embers.block_furnace":5,"stat.mineBlock.terraqueous.earth_ore":16,"stat.useItem.fp.wire":149,"stat.pickup.forestry.portable_alyzer":2,"stat.drop.forestry.ash":11,"stat.pickup.fp.color_iron_stair15":40,"stat.pickup.fp.color_iron_stair10":8,"stat.pickup.skyresources.fluiddropper":3,"stat.craftItem.primal.slat_oak":2,"stat.pickup.thermaldynamics.filter":2,"stat.mineBlock.refinedstorage.external_storage":5,"stat.craftItem.minecraft.wooden_pressure_plate":2,"stat.craftItem.refinedstorage.storage_housing":2,"stat.craftItem.flexibletools.swordi":4,"stat.mineBlock.magneticraft.battery":5,"stat.craftItem.primal.obsidian_plate":16,"stat.mineBlock.embers.item_transfer":3,"stat.pickup.tconstruct.ore":86,"stat.craftItem.embers.tinker_hammer":4,"stat.pickup.minecraft.snowball":152,"stat.pickup.storagedrawers.basicdrawers":25,"stat.useItem.minecraft.sticky_piston":9,"stat.pickup.exnihilocreatio.block_crucible":14,"stat.pickup.mist.clay_ball":40,"stat.pickup.mist.sponge_slime":40,"stat.pickup.fp.sword_neon":3,"stat.pickup.minecraft.stained_glass_pane":12,"stat.mineBlock.magneticraft.connector":70,"stat.pickup.fp.color_gitter_pane":63,"stat.pickup.thermalfoundation.armor.legs_lead":2,"stat.drop.advancedrocketry.rocketbuilder":1,"stat.pickup.libvulpes.elitemotor":1,"stat.craftItem.embers.ember_bore":2,"stat.drop.minecraft.glowstone":1,"stat.craftItem.buildcrafttransport.pipe_wood_power":9,"stat.craftItem.foundry.burnerheater":2,"stat.mineBlock.terraqueous.ender_table":1,"stat.useItem.fp.color_iron":188,"stat.craftItem.immcraft.rock":18,"stat.useItem.primal.desiccated_stone":49,"stat.damageTaken":30810,"stat.pickup.immersiveengineering.metal":84,"stat.mineBlock.astralsorcery.blocklens":12,"stat.pickup.mist.gravel":915,"stat.pickup.biomesoplenty.ash_block":2490,"stat.pickup.embers.item_pipe":100,"stat.pickup.minecraft.bed":5,"stat.craftItem.embers.mixer":2,"stat.useItem.roots.wildroot_item":2,"stat.pickup.minecraft.concrete":62,"stat.pickup.exnihilocreatio.item_seed_potato":1,"stat.pickup.minecraft.potato":55,"stat.mineBlock.embers.vacuum":11,"stat.useItem.astralsorcery.itemknowledgeshare":9,"stat.drop.botania.petal":25,"stat.drop.survivalist.rock":105,"stat.drop.primal.hardened_stone":1,"stat.useItem.fp.scrench":237,"stat.pickup.sparkshammers.hammer_craft":2,"stat.pickup.advancedrocketry.satellitecontrolcenter":1,"stat.drop.immersiveengineering.wirecoil":2,"stat.mineBlock.mist.acid_dirt_0":7,"stat.mineBlock.mist.acid_dirt_1":1,"stat.pickup.fp.modul_1":9,"stat.mineBlock.mist.acid_dirt_2":2,"stat.mineBlock.astralsorcery.blockwell":6,"stat.pickup.mist.niobium_ingot":678,"stat.pickup.advancedrocketry.structuretower":21,"stat.drop.terraqueous.flowers_single":3,"stat.pickup.thermalfoundation.storage":313,"stat.useItem.fp.color_glas":32,"stat.craftItem.extendedcrafting.material":113,"stat.useItem.minecraft.netherrack":4,"stat.craftItem.soot.stamp_nugget":1,"stat.pickup.thermalcultivation.watering_can":3,"stat.craftItem.buildcrafttransport.pipe_cobble_power":17,"stat.mineBlock.refinedstorage.grid":3,"stat.pickup.roots.terra_moss_spore":133,"stat.pickup.roots.chiseled_runestone":37,"stat.mineBlock.embers.item_pipe":83,"stat.pickup.fp.fp_lever":15,"stat.pickup.woot.upgrade":3,"stat.pickup.minecraft.torch":258,"stat.pickup.fp.erz_blocke":670,"stat.useItem.thermaldynamics.servo":39,"stat.mineBlock.embers.mech_core":4,"stat.pickup.mist.niobium_pickaxe":1,"stat.craftItem.primal.cinisclay_clump":36,"stat.mineBlock.immcraft.chest":21,"stat.mineBlock.exnihilocreatio.block_sieve":28,"stat.craftItem.primal.iron_workblade":1,"stat.drop.mist.rocks":31,"stat.pickup.exnihilocreatio.item_ore_ardite":242,"stat.useItem.terraqueous.sapling":2,"stat.drop.embers.ember_detector":1,"stat.useItem.minecraft.planks":38,"stat.pickup.enderstorage.ender_storage":21,"stat.pickup.embers.caminite_lever":21,"stat.craftItem.immersiveengineering.metal_device1":2,"stat.useItem.primal.rush_seeds":122,"stat.pickup.openblocks.elevator":7,"stat.pickup.minecraft.sand":1660,"stat.pickup.astralsorcery.blockinfusedwood":364,"stat.craftItem.botania.livingwoodbow":2,"stat.pickup.forestry.miner_bag":1,"stat.craftItem.embers.stairs_caminite_brick":8,"stat.pickup.earthworks.block_cob":27,"stat.mineBlock.biomesoplenty.ash_block":10201,"stat.mineBlock.forestry.engine_biogas":1,"stat.useItem.magneticraft.inserter":1,"stat.useItem.primal.lantern_empty":2,"stat.pickup.embers.nugget_bronze":9,"stat.useItem.rftools.storage_control_module":1,"stat.drop.buildcraftfactory.autoworkbench_item":1,"stat.killEntity.thermalfoundation.basalz":35,"stat.drop.botany.misc":2,"stat.mineBlock.biomesoplenty.dirt":1,"stat.craftItem.primal.diamond_axe":8,"stat.pickup.exnihilocreatio.block_barrel0":12,"stat.useItem.immersiveengineering.connector":88,"stat.craftItem.fp.e_furnace":1,"stat.pickup.exnihilocreatio.block_barrel1":2,"stat.pickup.xlfoodmod.lettuce_seeds":153,"stat.craftItem.magneticraft.stone_hammer":14,"stat.pickup.embers.stamper_base":6,"stat.pickup.astralsorcery.blockworldilluminator":1,"stat.pickup.embers.archaic_brick":90,"stat.pickup.minecraft.fence_gate":6,"stat.pickup.roots.terra_moss_ball":58,"stat.pickup.appliedenergistics2.charger":6,"stat.pickup.chisel.hardenedclay":37,"stat.useItem.buildcrafttransport.pipe_cobble_item":93,"stat.craftItem.minecraft.sand":995,"stat.craftItem.primal.scoria_stone":4,"stat.useItem.immersiveengineering.seed":101,"stat.drop.waterstrainer.strainer_base":1,"stat.mineBlock.exnihilocreatio.block_auto_sifter":8,"stat.craftItem.primal.wood_pin":290,"stat.pickup.botania.foresteye":3,"stat.pickup.mist.mushrooms_food":4,"stat.drop.actuallyadditions.item_coffee_seed":1,"stat.useItem.libvulpes.structuremachine":1,"stat.mineBlock.skyresources.sandynetherrack":3,"stat.useItem.forestry.wood_pile":236,"stat.pickup.xlfoodmod.pepper_seeds":2,"stat.pickup.embers.ember_detector":1,"stat.playOneMinute":17167253,"stat.pickup.tconstruct.rack":23,"stat.pickup.openblocks.sleeping_bag":1,"stat.mineBlock.botania.forestdrum":1,"stat.drop.chisel.basalt2":14,"stat.pickup.waterstrainer.strainer_survivalist_dense":2,"stat.mineBlock.mist.stone_porous":4,"stat.pickup.tconstruct.clear_stained_glass":2,"stat.mineBlock.minecraft.netherrack":46,"stat.drop.minecraft.flint":2,"stat.fallOneCm":212000,"stat.drop.minecraft.dye":17,"stat.pickup.fp.wr_receiver":13,"stat.craftItem.minecraft.chest":4,"stat.craftItem.earthworks.block_adobe":22,"stat.mineBlock.minecraft.lever":25,"stat.mineBlock.botania.livingrock":26,"stat.mineBlock.openblocks.auto_enchantment_table":4,"stat.pickup.minecraft.feather":3155,"stat.useItem.biomesoplenty.mud":2,"stat.drop.minecraft.concrete":1,"stat.pickup.forestry.carpenter":5,"stat.pickup.rftools.powercell_advanced":1,"stat.craftItem.libvulpes.productrod":60,"stat.craftItem.waterstrainer.strainer_survivalist_dense":21,"stat.pickup.botania.twigwand":1,"stat.useItem.minecraft.stone_pickaxe":224,"stat.craftItem.fp.wire":32,"stat.pickup.primal.logs_split_oak":45,"stat.killEntity.Rabbit":1,"stat.pickup.embers.stamp_plate":6,"stat.drop.primal.plant_fiber":3,"stat.drop.botania.manacookie":1,"stat.pickup.botania.specialflower":15,"stat.pickup.botania.pylon":17,"stat.useItem.roots.wood_hammer":9,"stat.useItem.skyresources.casing":1,"stat.mineBlock.exnihilocreatio.block_dust":1,"stat.craftItem.forestry.carpenter":2,"stat.useItem.primal.cauldron_ladle_lacquer":7,"stat.drop.primal.logs_split_oak":1,"stat.pickup.embers.ember_receiver":15,"stat.useItem.ironchest.iron_chest":35,"stat.useItem.exnihilocreatio.item_seed_cactus":1,"stat.craftItem.primal.thatching_wet":30,"stat.pickup.minecraft.log":2125,"stat.pickup.fp.dust":16,"stat.killEntity.primitivemobs.grovesprite":3,"stat.craftItem.embers.stamp_plate":1,"stat.pickup.transprot.dispatcher":5,"stat.craftItem.foundry.component":160,"stat.pickup.minecraft.wooden_door":11,"stat.mineBlock.mist.niobium_ore":2,"stat.craftItem.refinedstorage.crafter":1,"stat.pickup.fp.crystalenergycell":5,"stat.useItem.roots.chiseled_runestone":5,"stat.craftItem.tconstruct.metal":4,"stat.craftItem.fp.block_breaker":1,"stat.pickup.environmentaltech.structure_panel":129,"stat.craftItem.botania.pavement":108,"stat.useItem.buildcrafttransport.pipe_wood_power":20,"stat.useItem.primal.fish_clown_dried":8,"stat.pickup.botania.vial":1,"stat.sneakTime":372876,"stat.craftItem.primal.diamond_saw":2,"stat.craftItem.embers.ember_emitter":8,"stat.pickup.persistentbits.chunk_loader":3,"stat.useItem.minecraft.lapis_block":3,"stat.useItem.thermalfoundation.storage_alloy":1,"stat.pickup.embers.tinker_hammer":2,"stat.craftItem.buildcrafttransport.pipe_cobble_item":72,"stat.pickup.skyresources.combustionheater":8,"stat.craftItem.rftools.storage_control_module":1,"stat.mineBlock.environmentaltech.modifier_null":3,"stat.craftItem.skyresources.crucibleinserter":4,"stat.craftItem.immersiveengineering.connector":34,"stat.craftItem.botania.petal":62,"stat.swimOneCm":182399,"stat.craftItem.fp.modul_1":1,"stat.craftItem.fp.modul_2":1,"stat.mineBlock.botania.floatingspecialflower":4,"stat.pickup.roots.moontinged_seed":78,"stat.drop.astralsorcery.itemknowledgeshare":1,"stat.pickup.flexibletools.multi":99,"stat.killEntity.pixie":6,"stat.useItem.minecraft.dirt":1526,"stat.mineBlock.buildcraftfactory.tank":24,"stat.craftItem.magneticraft.conveyor_belt":32,"stat.craftItem.fp.zentrifuge":3,"stat.pickup.environmentaltech.void_res_miner_cont_2":6,"stat.pickup.environmentaltech.void_res_miner_cont_1":1,"stat.pickup.refinedstorage.controller":3,"stat.pickup.primal.thin_slab_glass":3,"stat.mineBlock.roots.bonfire":2,"stat.mineBlock.minecraft.carpet":7,"stat.drop.minecraft.fence":1,"stat.pickup.minecraft.clay":181,"stat.pickup.embers.aspectus_iron":1,"stat.craftItem.environmentaltech.structure_frame_1":44,"stat.craftItem.actuallyadditions.item_food":7,"stat.drop.minecraft.log":17,"stat.pickup.minecraft.mutton":424,"stat.pickup.actuallyadditions.block_testifi_bucks_green_wall":16,"stat.pickup.embers.stamp_bar":3,"stat.craftItem.environmentaltech.litherite":20,"stat.useItem.minecraft.lever":86,"stat.mineBlock.fp.ind_neon_furn":14,"stat.pickup.primal.flint_shears":1,"stat.pickup.buildcrafttransport.pipe_wood_fluid":2,"stat.pickup.chisel.chisel_diamond":1,"stat.craftItem.minecraft.red_sandstone":32,"stat.pickup.minecraft.redstone_lamp":3,"stat.pickup.buildcraftfactory.autoworkbench_item":4,"stat.pickup.buildcrafttransport.pipe_void_item":2,"stat.craftItem.buildcrafttransport.pipe_diamond_item":112,"stat.craftItem.jaff.iron_hook":2,"stat.mineBlock.mist.acid_grass_0":2,"stat.mineBlock.mist.acid_grass_1":1,"stat.pickup.fp.plasma_generator_on":1,"stat.pickup.primal.rock_stone":7,"stat.useItem.astralsorcery.blockmarble":168,"stat.pickup.xlfoodmod.corn_seeds":72,"stat.craftItem.environmentaltech.structure_panel":24,"stat.drop.forestry.phosphor":13,"stat.useItem.buildcraftsilicon.laser":16,"stat.pickup.actuallyadditions.item_misc":2,"stat.pickup.advancedrocketry.satelliteidchip":1,"stat.pickup.exnihilocreatio.item_material":6,"stat.craftItem.skyresources.lifeinfuser":4,"stat.killEntity.Endermite":12,"stat.useItem.fp.extern_cooler":5,"stat.craftItem.buildcraftfactory.tank":16,"stat.pickup.fp.partpress":3,"stat.craftItem.magneticraft.copper_coil":3,"stat.pickup.minecraft.stone_button":2,"stat.mineBlock.buildcraftfactory.autoworkbench_item":4,"stat.pickup.botania.hourglass":13,"stat.craftItem.primal.stone_gallagher":3,"stat.pickup.immersiveengineering.aluminum_scaffolding_stairs1":2,"stat.useItem.thermalfoundation.storage":9,"stat.pickup.foundry.mold":54,"stat.pickup.minecraft.gravel":52,"stat.useItem.exnihilocreatio.block_dust":1,"stat.useItem.libvulpes.linker":2,"stat.craftItem.survivalist.rack":2,"stat.drop.flexibletools.swordi":3,"stat.pickup.botania.teruterubozu":3,"stat.useItem.minecraft.stained_glass_pane":7,"stat.killEntity.primal:bear_black":2,"stat.useItem.tconstruct.tooltables":2,"stat.craftItem.earthworks.block_wood_shingle":72,"stat.useItem.minecraft.piston":4,"stat.useItem.mist.niobium_pickaxe":54,"stat.pickup.minecraft.spider_eye":4,"stat.craftItem.exnihilocreatio.block_axle_stone":24,"stat.pickup.actuallyadditions.item_helm_crystal_green":6,"stat.craftItem.immersiveengineering.metal_decoration1":12,"stat.pickup.buildcrafttransport.pipe_void_fluid":2,"stat.pickup.xnet.netcable":15,"stat.craftItem.immersiveengineering.metal_decoration0":10,"stat.pickup.minecraft.leather":588,"stat.entityKilledBy.ancient_golem":1,"stat.mineBlock.immersiveengineering.conveyor":8,"stat.pickup.fp.huge_mycel":7,"stat.useItem.botania.manacookie":29,"stat.pickup.botania.distributor":2,"stat.pickup.oreberries.silver_oreberry":2,"stat.craftItem.minecraft.glass":1274,"stat.craftItem.minecraft.cauldron":2,"stat.sleepInBed":49,"stat.mineBlock.jaff.tank":6,"stat.killEntity.Cow":218,"stat.useItem.buildcraftcore.engine":28,"stat.pickup.primal.hardened_stone":1,"stat.pickup.embers.vacuum":11,"stat.craftItem.tinkerskyblock.wooden_hopper":14,"stat.pickup.minecraft.piston":11,"stat.walkOneCm":38162061,"stat.useItem.jaff.fish_bucket_clownfish":1,"stat.craftItem.actuallyadditions.item_pants_crystal_green":4,"stat.craftItem.tconstruct.throwball":11,"stat.useItem.embers.hoe_lead":10,"stat.craftItem.actuallyadditions.item_crystal":18,"stat.pickup.refinedstorage.disk_drive":3,"stat.drop.chisel.stonebrick":4,"stat.mineBlock.environmentaltech.void_res_miner_cont_1":1,"stat.drop.survivalist.jerky":3,"stat.pickup.minecraft.stone":684,"stat.mineBlock.botania.distributor":2,"stat.pickup.primal.night_stone":16,"stat.useItem.jaff.fish_bucket_salmon":1,"stat.pickup.minecraft.gold_ingot":4,"stat.useItem.fp.color_gitter_pane":12,"stat.pickup.forestry.apatite":187,"stat.mineBlock.minecraft.cactus":77,"stat.craftItem.buildcrafttransport.pipe_obsidian_item":16,"stat.craftItem.embers.codex":2,"stat.drop.everlastingabilities.ability_totem":3,"stat.mineBlock.minecraft.redstone_torch":5,"stat.useItem.biomesoplenty.sapling_0":236,"stat.drop.yabba.item_barrel":1,"stat.pickup.minecraft.quartz":173,"stat.pickup.botania.pool":14,"stat.craftItem.skyresources.crucible":4,"stat.useItem.chisel.factory":1,"stat.pickup.minecraft.lava_bucket":2,"stat.pickup.rftools.storage_module_tablet":26,"stat.craftItem.minecraft.brick":17,"stat.mineBlock.minecraft.stone":10,"stat.useItem.minecraft.sandstone":91,"stat.craftItem.mist.filter_coal":1,"stat.pickup.actuallyadditions.item_boots_crystal_green":2,"stat.pickup.xlfoodmod.fried_egg":1,"stat.useItem.fp.spaceship":59,"stat.useItem.magneticraft.iron_pipe":266,"stat.pickup.primal.fish_puffer_dried":16,"stat.drop.minecraft.redstone":3,"stat.mineBlock.environmentaltech.laser_core":4,"stat.craftItem.forestry.fertilizer_compound":10,"stat.useItem.advancedrocketry.launchpad":66,"stat.pickup.tconstruct.faucet":4,"stat.pickup.primal.pelt_bear_black":1,"stat.craftItem.fp.fuelcell":4,"stat.craftItem.fp.color_glas":40,"stat.useItem.botany.trowel_diamond":3,"stat.useItem.buildcrafttransport.pipe_diamond_item":30,"stat.craftItem.minecraft.stone_axe":15,"stat.pickup.embers.codex":1,"stat.pickup.minecraft.bucket":22,"stat.pickup.terraqueous.ender_table":2,"stat.pickup.minecraft.brown_mushroom":4,"stat.mineBlock.exnihilocreatio.block_waterwheel":12,"stat.pickup.botania.manacookie":64,"stat.mineBlock.xnet.connector":2,"stat.pickup.astralsorcery.blocklens":16,"stat.useItem.minecraft.iron_pickaxe":254,"stat.pickup.embers.ashen_stone":9,"stat.mineBlock.foundry.machine":42,"stat.pickup.minecraft.light_weighted_pressure_plate":9,"stat.craftItem.simplyjetpacks.itemjetpack":1,"stat.mineBlock.terraqueous.plants":1,"stat.pickup.fp.composite_boots":1,"stat.pickup.jaff.tank":6,"stat.craftItem.embers.beam_cannon":2,"stat.mineBlock.immersiveengineering.wooden_device0":3,"stat.pickup.tinkerskyblock.wooden_hopper":5,"stat.mineBlock.minecraft.wooden_button":1,"stat.mineBlock.immersiveengineering.wooden_device1":7,"stat.useItem.exnihilocreatio.item_seed_potato":1,"stat.mineBlock.botania.dreamwood":8,"stat.useItem.minecraft.fence":237,"stat.pickup.actuallyadditions.item_crystal":89,"stat.mineBlock.minecraft.fence":7,"stat.useItem.botania.twigwand":355,"stat.pickup.minecraft.lever":191,"stat.deaths":13,"stat.drop.flexibletools.tool_upgrade_skill":2,"stat.killEntity.sprout":2,"stat.drop.waterstrainer.strainer_survivalist_dense":2,"stat.pickup.thermalfoundation.wrench":3,"stat.mineBlock.buildcraftsilicon.laser":29,"stat.craftItem.modularmachinery.blockcasing":9,"stat.pickup.primal.pelt_wolf":3,"stat.mineBlock.biomesoplenty.bamboo":1,"stat.pickup.minecraft.iron_sword":3,"stat.pickup.thermalexpansion.augment":1,"stat.pickup.minecraft.gold_nugget":37,"stat.pickup.botania.lexicon":1,"stat.pickup.primal.hibachi":2,"stat.pickup.primal.ortho_stone":11,"stat.crouchOneCm":317706,"stat.pickup.libvulpes.productdust":664,"stat.mineBlock.environmentaltech.structure_panel":41,"stat.drop.primal.urushi_ground":53,"stat.craftingTableInteraction":11430,"stat.mineBlock.primal.desiccated_stone":34,"stat.craftItem.botania.elfglass":3,"stat.mineBlock.tconstruct.rack":24,"stat.pickup.minecraft.repeater":8,"stat.drop.backpacks16840.backpack":2,"stat.mineBlock.magneticraft.inserter":5,"stat.craftItem.buildcrafttransport.waterproof":18,"stat.mineBlock.biomesoplenty.plant_1":9,"stat.mineBlock.biomesoplenty.plant_0":4,"stat.pickup.biomesoplenty.plant_1":8,"stat.craftItem.tconstruct.slime_congealed":8,"stat.pickup.primal.cauldron":1,"stat.pickup.skyresources.alchemyitemcomponent":542,"stat.flowerPotted":1,"stat.useItem.libvulpes.forgepowerinput":2,"stat.mineBlock.embers.mixer":7,"stat.mineBlock.biomesoplenty.leaves_1":888,"stat.pickup.primal.suet":577,"stat.craftItem.biomesoplenty.plant_0":1,"stat.pickup.tconstruct.pickaxe":3,"stat.pickup.astralsorcery.blockwell":12,"stat.pickup.refinedstorage.processor":21,"stat.pickup.minecraft.chicken":12,"stat.pickup.roots.wood_knife":1,"stat.craftItem.flexibletools.multi":2,"stat.killEntity.drone":22,"stat.mineBlock.botania.pylon":16,"stat.mineBlock.embers.stamper_base":6,"stat.drop.minecraft.fish":4,"stat.craftItem.minecraft.bucket":8,"stat.pickup.magneticraft.stone_hammer":2,"stat.pickup.minecraft.stone_sword":2,"stat.mineBlock.botania.teruterubozu":3,"stat.craftItem.minecraft.fishing_rod":2,"stat.mineBlock.storagedrawers.controller":3,"stat.pickup.minecraft.book":13,"stat.drop.forestry.portable_alyzer":2,"stat.useItem.carryon.entity_item":27,"stat.drop.buildcraftfactory.pump":1,"stat.useItem.botania.pylon":3,"stat.drop.botania.twigwand":1,"stat.pickup.primal.wolf_meat_raw":4,"stat.useItem.survivalist.rack":1,"stat.mineBlock.astralsorcery.blockworldilluminator":1,"stat.drop.primal.night_stone":2,"stat.craftItem.primal.cauldron":2,"stat.craftItem.environmentaltech.void_ore_miner_cont_1":2,"stat.pickup.minecraft.bookshelf":6,"stat.pickup.environmentaltech.laser_lens_colored":3,"stat.mineBlock.minecraft.pumpkin":4,"stat.pickup.minecraft.stone_pickaxe":1,"stat.mineBlock.rftools.screen_controller":1,"stat.craftItem.thermalexpansion.cell":4,"stat.pickup.buildcrafttransport.pipe_clay_item":10,"stat.mineBlock.minecraft.concrete":52,"stat.pickup.bibliocraft.shelf":2,"stat.craftItem.thermalfoundation.armor.plate_lead":3,"stat.craftItem.modularmachinery.blockinputbus":4,"stat.craftItem.fp.metal_gitter_block":6,"stat.useItem.minecraft.stone_slab2":3697,"stat.useItem.jaff.tank":20,"stat.useItem.fp.grenade_launcher":6,"stat.craftItem.minecraft.furnace":2,"stat.craftItem.biomesoplenty.mud":410,"stat.craftItem.xlfoodmod.baguette":4,"stat.pickup.primal.torch_wood":480,"stat.useItem.biomesoplenty.mudball":107,"stat.drop.botania.cosmetic":1,"stat.drop.skyresources.alchemyitemcomponent":2,"stat.pickup.foundry.castingtable":26,"stat.craftItem.advancedrocketry.satellitecontrolcenter":1,"stat.mineBlock.terraqueous.flowers_cluster":3,"stat.pickup.fp.techtable":27,"stat.useItem.botania.pavement4stairs":6,"stat.pickup.mist.filter_coal":296,"stat.craftItem.fp.largebattery":2,"stat.useItem.xlfoodmod.taco_salad":9,"stat.pickup.thermaldynamics.duct_0":337,"stat.pickup.roots.runestone":93,"stat.useItem.tconstruct.rack":6,"stat.useItem.buildcrafttransport.pipe_iron_item":59,"stat.mineBlock.mist.gravel":504,"stat.drop.botania.livingwood":16,"stat.pickup.buildcraftfactory.pump":3,"stat.useItem.actuallyadditions.block_display_stand":6,"stat.craftItem.waterstrainer.strainer_survivalist_reinforced":17,"stat.pickup.magneticraft.inserter":5,"stat.pickup.immersiveengineering.tool":10,"stat.useItem.carryon.tile_item":218,"stat.drop.sparkshammers.excavator_stone":1,"stat.useItem.minecraft.snowball":40,"stat.useItem.magneticraft.copper_coil":247,"stat.useItem.terraqueous.flowers_single":1,"stat.pickup.modularmachinery.itemblueprint":1,"stat.waystones:waystonesActivated":21,"stat.craftItem.embers.crystal_ember":13,"stat.useItem.botania.pavement":192,"stat.craftItem.minecraft.dye":700,"stat.pickup.embers.crystal_ember":5,"stat.pickup.minecraft.wheat":715,"stat.craftItem.minecraft.sandstone":298,"stat.mineBlock.immersiveengineering.metal_device0":41,"stat.drop.botania.vial":1,"stat.mineBlock.immersiveengineering.metal_device1":14,"stat.craftItem.fp.brennstoff_generator":6,"stat.drop.astralsorcery.itemcraftingcomponent":38,"stat.pickup.minecraft.sign":9,"stat.pickup.immersivepetroleum.metal_device":1,"stat.useItem.minecraft.heavy_weighted_pressure_plate":2,"stat.pickup.xlfoodmod.onion":264,"stat.useItem.immersiveengineering.stone_decoration":132,"stat.pickup.minecraft.iron_ingot":334,"stat.useItem.primal.thin_slab_glass":25,"stat.craftItem.minecraft.lever":94,"stat.craftItem.refinedstorage.grid":2,"stat.pickup.minecraft.gunpowder":14,"stat.useItem.magneticraft.conveyor_belt":5,"stat.drop.embers.codex":3,"stat.mineBlock.magneticraft.solar_panel":9,"stat.pickup.minecraft.cookie":25,"stat.drop.magneticraft.stone_hammer":1,"stat.pickup.buildcrafttransport.pipe_iron_item":23,"stat.pickup.biomesoplenty.grass":1,"stat.brewingstandInteraction":1,"stat.craftItem.advgenerators.controller":4,"stat.mineBlock.minecraft.red_flower":1,"stat.mineBlock.fp.partpress":3,"stat.pickup.astralsorcery.blockcustomore":6,"stat.pickup.immersivepetroleum.schematic":2,"stat.pickup.mist.dirt_c":1,"stat.craftItem.buildcraftcore.gear_wood":129,"stat.craftItem.primal.iron_pin":8,"stat.pickup.minecraft.rabbit_hide":4,"stat.pickup.mist.dirt_t":68,"stat.useItem.thermalexpansion.augment":14,"stat.craftItem.thermalfoundation.armor.helmet_tin":2,"stat.craftItem.primal.plant_fiber":1024,"stat.pickup.buildcrafttransport.pipe_wood_item":26,"stat.pickup.mist.sponge_fibre":7,"stat.drop.everlastingabilities.ability_bottle":2,"stat.pickup.magneticraft.rocky_chunks":61,"stat.craftItem.fp.board_computer":1,"stat.useItem.minecraft.lava_bucket":26,"stat.craftItem.advancedrocketry.ic":26,"stat.useItem.chisel.hardenedclay1":1,"stat.pickup.teslacorelib.machine_case":2,"stat.drop.advancedrocketry.pressuretank":1,"stat.useItem.minecraft.concrete":38,"stat.killEntity.Stray":43,"stat.drop.fp.spaceship":8,"stat.drop.primal.adobebrick_dry":1,"stat.pickup.terraqueous.plants":8,"stat.craftItem.minecraft.cookie":32,"stat.mobKills":841,"stat.mineBlock.earthworks.block_wood_shingle":2,"stat.mineBlock.woot.cell":1,"stat.pickup.minecraft.diamond":12,"stat.drop.biomesoplenty.dirt":4,"stat.drop.thermalexpansion.tank":3,"stat.craftItem.embers.dawnstone_anvil":2,"stat.pickup.botania.livingrock":162,"stat.mineBlock.mist.filter_coal_ore":1,"stat.mineBlock.primal.ortho_stone":4,"stat.pickup.primal.diamond_knapp":98,"stat.useItem.biomesoplenty.ash_block":3719,"stat.craftItem.flexibletools.tool_upgrade_transport":4,"stat.drop.tconstruct.pickaxe":1,"stat.craftItem.exnihilocreatio.block_dust":3411,"stat.craftItem.advancedrocketry.spacestationchip":1,"stat.pickup.minecraft.glowstone_dust":332,"stat.mineBlock.roots.chiseled_runestone":19,"stat.useItem.botania.pool":3,"stat.craftItem.ceramics.clay_shears":1,"stat.drop.astralsorcery.itemskyresonator":1,"stat.craftItem.botania.hourglass":6,"stat.useItem.thermalfoundation.upgrade":20,"stat.pickup.compactmachines3.fieldprojector":13,"stat.pickup.libvulpes.forgepowerinput":2,"stat.pickup.sparkshammers.hammer_stone":1,"stat.craftItem.embers.stamper_base":2,"stat.pickup.minecraft.chainmail_chestplate":4,"stat.useItem.chisel.basalt":136,"stat.drop.chisel.offsettool":1,"stat.drop.thermaldynamics.duct_0":1,"stat.craftItem.minecraft.slime":2,"stat.useItem.environmentaltech.solar_cell_pladium":8,"stat.hopperInspected":1196,"stat.drop.minecraft.diamond":19,"stat.mineBlock.terraqueous.doodads":158,"stat.pickup.thermalexpansion.cell":21,"stat.useItem.tconstruct.channel":8,"stat.craftItem.libvulpes.productgear":4,"stat.drop.minecraft.diamond_block":2,"stat.pickup.buildcrafttransport.pipe_quartz_power":31,"stat.drop.astralsorcery.blockblackmarble":1,"stat.mineBlock.fp.brennstoff_generator":4,"stat.craftItem.advancedrocketry.loader":4,"stat.craftItem.thermalfoundation.material":1400,"stat.craftItem.advancedrocketry.rocketbuilder":1,"stat.craftItem.skyresources.alchemicalinfusionstone":5,"stat.pickup.fp.beam":7,"stat.drop.biomesoplenty.ash":84,"stat.useItem.minecraft.cooked_mutton":21,"stat.mineBlock.botania.alfheimportal":3,"stat.pickup.fp.flash_server":85,"stat.pickup.skyresources.casing":7,"stat.useItem.thermaldynamics.duct_0":607,"stat.mineBlock.embers.ashen_stone":1,"stat.useItem.botania.petal":17,"stat.craftItem.minecraft.fence_gate":6,"stat.useItem.betterbuilderswands.wanddiamond":80,"stat.pickup.minecraft.pumpkin_seeds":3,"stat.useItem.buildcrafttransport.pipe_wood_item":40,"stat.pickup.environmentaltech.lonsdaleite_crystal":124,"stat.craftItem.tconstruct.scythe":1,"stat.pickup.simplyjetpacks.itemjetpack":3,"stat.useItem.xlfoodmod.tomato_seeds":28,"stat.pickup.fp.mendel_seed":3,"stat.useItem.chisel.laboratory":89,"stat.pickup.buildcrafttransport.pipe_obsidian_item":1,"stat.pickup.minecraft.blaze_rod":4,"stat.craftItem.openblocks.sleeping_bag":2,"stat.pickup.fp.spaceship":103,"stat.craftItem.primal.silk_cordage":19,"stat.useItem.immersiveengineering.wooden_device1":3,"stat.drop.minecraft.chest":3,"stat.mineBlock.mist.stone":6,"stat.pickup.botania.alfheimportal":3,"stat.craftItem.primal.iron_mesh":156,"stat.pickup.minecraft.netherrack":1110,"stat.mineBlock.botania.specialflower":10,"stat.pickup.minecraft.pumpkin":4,"stat.useItem.minecraft.fish":2,"stat.drop.minecraft.hopper":1,"stat.pickup.embers.ember_bore":8,"stat.craftItem.fp.scanner_block":1,"stat.mineBlock.earthworks.block_cob":30,"stat.useItem.primal.fish_cod_dried":14,"stat.useItem.modularmachinery.itemblueprint":10,"stat.useItem.environmentaltech.solar_cell_litherite":1,"stat.craftItem.embers.stamp_plate_raw":2,"stat.useItem.forestry.fertilizer_compound":21,"stat.pickup.thermalexpansion.device":3,"stat.dropperInspected":105,"stat.pickup.earthworks.item_sand":61,"stat.drop.minecraft.bone":1,"stat.drop.woot.stygianironplate":1,"stat.craftItem.minecraft.wooden_button":2,"stat.craftItem.tconstruct.materials":18,"stat.mineBlock.botania.pool":14,"stat.mineBlock.primal.ferro_stone":12,"stat.mineBlock.buildcrafttransport.pipe_diamond_fluid":272,"stat.pickup.waystones.waystone":24,"stat.mineBlock.forestry.fermenter":2,"stat.useItem.minecraft.torch":767,"stat.useItem.minecraft.log":60,"stat.useItem.primal.brickform":10,"stat.pickup.biomesoplenty.coral":144,"stat.useItem.embers.alchemy_pedestal":1,"stat.craftItem.minecraft.crafting_table":65,"stat.mineBlock.mist.bio_shale_ore":7,"stat.pickup.astralsorcery.blockborehead":1,"stat.drop.survivalist.rock_ore":10,"stat.craftItem.magneticraft.multiblock_parts":4,"stat.mineBlock.chisel.stonebrick":5,"stat.useItem.minecraft.cooked_fish":31,"stat.pickup.primal.lantern_empty":1,"stat.craftItem.libvulpes.structuremachine":7,"stat.drop.minecraft.planks":201,"stat.useItem.embers.pump":31,"stat.pickup.minecraft.sapling":4,"stat.craftItem.refinedstorage.pattern":12,"stat.pickup.mist.niobium_ore":34,"stat.pickup.minecraft.beetroot":10,"stat.pickup.roots.aubergine_seeds":142,"stat.useItem.minecraft.wooden_pressure_plate":1,"stat.craftItem.fp.itemerze":367,"stat.pickup.minecraft.rabbit":1,"stat.pickup.refinedstorage.exporter":1,"stat.pickup.fp.cristall":545,"stat.drop.minecraft.yellow_flower":6,"stat.pickup.minecraft.yellow_flower":14,"stat.pickup.environmentaltech.void_ore_miner_cont_2":5,"stat.pickup.environmentaltech.void_ore_miner_cont_1":4,"stat.pickup.environmentaltech.void_ore_miner_cont_4":1,"stat.pickup.environmentaltech.void_ore_miner_cont_3":1,"stat.mineBlock.forestry.ffarm":38,"stat.pickup.minecraft.bone":269,"stat.craftItem.ceramics.unfired_clay":88,"stat.pickup.immersiveengineering.wooden_device1":7,"stat.pickup.minecraft.redstone_torch":8,"stat.pickup.embers.shard_ember":81,"stat.useItem.immersiveengineering.conveyor":4,"stat.craftItem.waterstrainer.strainer_survivalist":14,"stat.pickup.immersiveengineering.wooden_device0":3,"stat.mineBlock.fp.wire":153,"stat.mineBlock.forestry.carpenter":5,"stat.drop.astralsorcery.blockaltar":1,"stat.pickup.refinedstorage.external_storage":5,"stat.craftItem.forestry.ash":1053,"stat.craftItem.embers.item_dropper":2,"stat.pickup.rftools.storage_terminal":1,"stat.pickup.minecraft.golden_helmet":5,"stat.craftItem.flexibletools.tool_upgrade_skill":6,"stat.craftItem.skyresources.condenser":6,"stat.pickup.primal.terraclay_clump":1,"stat.craftItem.storagedrawers.upgrade_storage":8,"stat.craftItem.environmentaltech.laser_core":4,"stat.mineBlock.magneticraft.iron_pipe":8,"stat.craftItem.terraqueous.item_main":899,"stat.pickup.botania.forestdrum":2,"stat.pickup.skyresources.crucible":6,"stat.craftItem.minecraft.trapdoor":14,"stat.pickup.everlastingabilities.ability_totem":211,"stat.pickup.exnihilocreatio.item_seed_cactus":1,"stat.craftItem.minecraft.glass_bottle":6,"stat.pickup.mist.bio_shale":44,"stat.useItem.minecraft.cooked_beef":176,"stat.pickup.minecraft.cactus":179,"stat.craftItem.modularmachinery.blockfluidinputhatch":1,"stat.useItem.fp.erse":248,"stat.ae2.TurnedCranks":306,"stat.pickup.minecraft.redstone":798,"stat.pickup.embers.aspectus_copper":1,"stat.craftItem.minecraft.book":1,"stat.pickup.minecraft.mossy_cobblestone":11,"stat.pickup.xlfoodmod.lasagne":5,"stat.pickup.minecraft.cake":1,"stat.drop.flexibletools.axi":1,"stat.pickup.minecraft.carpet":17,"stat.pickup.forestry.honey_drop":1,"stat.mineBlock.actuallyadditions.block_display_stand":4,"stat.pickup.openblocks.trophy":7,"stat.craftItem.refinedstorage.core":7,"stat.craftItem.tconstruct.soil":50,"stat.craftItem.jaff.wooden_fishing_rod":2,"stat.pickup.fp.color_gitter_stair15":37,"stat.mineBlock.tinkerskyblock.wooden_hopper":5,"stat.useItem.minecraft.sea_lantern":21,"stat.pickup.biomesoplenty.terrestrial_artifact":5,"stat.drop.exnihilocreatio.block_barrel0":2,"stat.craftItem.botania.manaresource":23,"stat.mineBlock.fp.beam":7,"stat.drop.astralsorcery.blockborehead":1,"stat.pickup.rftools.storage_scanner":3,"stat.pickup.biomesoplenty.ash":71856,"stat.craftItem.thermalexpansion.dynamo":2,"stat.craftItem.embers.pump":4,"stat.pickup.minecraft.grass":1,"stat.pickup.forestry.logs.3":3,"stat.craftItem.minecraft.clay_ball":545,"stat.pickup.terraqueous.trunk2":4,"stat.mineBlock.refinedstorage.importer":2,"stat.drop":2010,"stat.craftItem.actuallyadditions.item_misc":50,"stat.killEntity.Sheep":199,"stat.mineBlock.earthworks.block_concrete":34,"stat.mineBlock.xnet.router":2,"stat.pickup.botany.misc":2070,"stat.killEntity.cod":3,"stat.mineBlock.botania.doubleflower2":6,"stat.useItem.immersiveengineering.tool":17,"stat.mineBlock.botania.doubleflower1":1,"stat.craftItem.refinedstorage.storage_part":25,"stat.pickup.openblocks.xp_drain":2,"stat.killEntity.Slime":40,"stat.craftItem.embers.block_caminite_brick":28,"stat.mineBlock.minecraft.deadbush":1,"stat.drop.teslathingies.compound_maker":2,"stat.pickup.everlastingabilities.ability_bottle":5,"stat.pickup.forestry.wood_pile":39,"stat.pickup.earthworks.block_wood_shingle":2,"stat.craftItem.embers.archaic_circuit":2,"stat.drop.minecraft.glass":5,"stat.useItem.minecraft.redstone_lamp":30,"stat.killEntity.fairy":14,"stat.craftItem.minecraft.iron_bars":368,"stat.pickup.embers.aspectus_dawnstone":8,"stat.pickup.magneticraft.solar_mirror":1,"stat.pickup.fp.zentrifuge":1,"stat.useItem.sparkshammers.hammer_stone":489,"stat.craftItem.minecraft.netherbrick":55,"stat.pickup.environmentaltech.laser_core":15,"stat.pickup.minecraft.oak_stairs":2,"stat.drop.biomesoplenty.ash_block":92,"stat.craftItem.minecraft.bowl":4,"stat.useItem.exnihilocreatio.item_seed_sugarcane":1,"stat.killEntity.FP-Gehuf":1,"stat.craftItem.buildcraftfactory.pump":1,"stat.pickup.embers.alchemy_tablet":4,"stat.craftItem.minecraft.stone_shovel":53,"stat.pickup.embers.mixer":7,"stat.pickup.minecraft.stick":519,"stat.pickup.magneticraft.battery":6,"stat.useItem.primal.fish_salmon_dried":47,"stat.drop.sparkshammers.hammer_stone":1,"stat.pickup.biomesoplenty.sapling_0":280,"stat.pickup.environmentaltech.modifier_piezo":4,"stat.pickup.primal.scoria_stone":87,"stat.pickup.primal.schist_green_stone":25,"stat.drop.minecraft.iron_block":2,"stat.pickup.primal.rush_seeds":195,"stat.pickup.fp.ind_neon_furn":14,"stat.drop.earthworks.item_dirt":3,"stat.mineBlock.botania.foresteye":3,"stat.pickup.primal.flint_shovel":1,"stat.pickup.fp.wire":155,"stat.useItem.botany.trowel_wood":6,"stat.pickup.thermaldynamics.servo":41,"stat.drop.minecraft.deadbush":6,"stat.drop.tconstruct.rack":1,"stat.useItem.primal.flint_pickaxe":168,"stat.drop.primal.torch_wood":1,"stat.pickup.minecraft.concrete_powder":3,"stat.craftItem.exnihilocreatio.block_barrel0":3,"stat.mineBlock.botania.hourglass":13,"stat.pickup.embers.ember_emitter":7,"stat.pickup.fp.assembly_table":2,"stat.mineBlock.environmentaltech.solar_cell_litherite":9,"stat.mineBlock.forestry.wood_pile":14,"stat.pickup.embers.stamp_flat":1,"stat.useItem.xlfoodmod.lasagne":4,"stat.mineBlock.tconstruct.channel":14,"stat.pickup.mist.tree_sapling":4,"stat.drop.forge.bucketfilled":1,"stat.craftItem.actuallyadditions.item_dust":31,"stat.pickup.botania.manatablet":36,"stat.pickup.immersiveengineering.conveyor":10,"stat.drop.minecraft.feather":25,"stat.pickup.environmentaltech.erodium_crystal":357,"stat.mineBlock.industrialforegoing.crop_recolector":1,"stat.mineBlock.environmentaltech.laser_lens_crystal":1,"stat.drop.biomesoplenty.turnip_seeds":5,"stat.pickup.environmentaltech.solar_cell_litherite":61,"stat.pickup.exnihilocreatio.block_dust":254,"stat.drop.biomesoplenty.gem":24,"stat.useItem.embers.pipe":94,"stat.useItem.tconstruct.throwball":2,"stat.mineBlock.minecraft.wooden_slab":3,"stat.pickup.primal.wolf_head_item":3,"stat.drop.minecraft.sand":1,"stat.drop.flexibletools.picki":2,"stat.craftItem.magneticraft.floppy_disk":12,"stat.drop.minecraft.gold_ingot":4,"stat.mineBlock.openblocks.trophy":7,"stat.craftItem.forestry.fertilizer_bio":1,"stat.pickup.primal.obsidian_plate":3,"stat.pickup.valkyrielib.guide":2,"stat.mineBlock.tconstruct.clear_glass":18,"stat.pickup.embers.bin":4,"stat.craftItem.minecraft.bed":1,"stat.useItem.environmentaltech.modifier_speed":3,"stat.craftItem.buildcrafttransport.pipe_wood_fluid":2,"stat.pickup.fp.color_iron_fence":5,"stat.useItem.roots.runestone_brick":11,"stat.drop.refinedstorage.processor":1,"stat.pickup.thermalfoundation.material":10348,"stat.useItem.minecraft.pumpkin_seeds":2,"stat.craftItem.embers.stamp_bar_raw":4,"stat.killEntity.ZombieVillager":64,"stat.useItem.waterstrainer.strainer_base":12,"stat.craftItem.primal.iron_clippers":2,"stat.pickup.minecraft.beef":560,"stat.pickup.chisel.stonebrick":147,"stat.useItem.primal.tall_grass_seeds":3,"stat.pickup.skyresources.sandynetherrack":78,"stat.pickup.fp.core":1,"stat.pickup.actuallyadditions.block_testifi_bucks_white_wall":15,"stat.useItem.biomesoplenty.dried_sand":1,"stat.craftItem.minecraft.gunpowder":232,"stat.mineBlock.embers.ember_activator":2,"stat.pickup.rftools.machine_frame":3,"stat.useItem.xlfoodmod.onion":12,"stat.craftItem.minecraft.dropper":6,"stat.craftItem.advancedrocketry.lens":1,"stat.useItem.minecraft.dye":139,"stat.pickup.magneticraft.dusts":889,"stat.mineBlock.enderstorage.ender_storage":21,"stat.drop.primal.cauldron_ladle_lacquer":1,"stat.pickup.primal.drain_scoria":1,"stat.pickup.actuallyadditions.item_dust":1418,"stat.pickup.magneticraft.iron_pipe":8,"stat.mineBlock.embers.item_dropper":5,"stat.pickup.refinedstorage.cable":17,"stat.pickup.astralsorcery.blockmarblestairs":6,"stat.mineBlock.minecraft.tallgrass":59,"stat.craftItem.minecraft.light_weighted_pressure_plate":6,"stat.pickup.immersiveengineering.material":1983,"stat.useItem.refinedstorage.cable":9,"stat.pickup.environmentaltech.ionite_crystal":632,"stat.pickup.magneticraft.ingots":69,"stat.useItem.actuallyadditions.item_food":7,"stat.useItem.embers.ashen_stone":33,"stat.drop.minecraft.iron_pickaxe":1,"stat.craftItem.refinedstorage.portable_grid":1,"stat.pickup.chisel.basalt2":4538,"stat.mineBlock.fp.cristall":144,"stat.mineBlock.minecraft.chest":118,"stat.pickup.earthworks.block_concrete":79,"stat.drop.embers.tinker_hammer":3,"stat.mineBlock.minecraft.hardened_clay":3,"stat.craftItem.minecraft.hopper":19,"stat.mineBlock.advancedrocketry.loader":4,"stat.pickup.embers.item_dropper":5,"stat.drop.minecraft.concrete_powder":1,"stat.pickup.foundry.burnerheater":2,"stat.pickup.astralsorcery.blockcustomsandore":248,"stat.pickup.embers.alchemy_pedestal":5,"stat.mineBlock.biomesoplenty.mud":1,"stat.useItem.minecraft.reeds":18,"stat.mineBlock.refinedstorage.portable_grid":3,"stat.pickup.fp.scrench":1,"stat.pickup.minecraft.wheat_seeds":883,"stat.pickup.flexibletools.picki":1,"stat.pickup.fp.scanner_block":2,"stat.pickup.actuallyadditions.block_atomic_reconstructor":3,"stat.pickup.minecraft.poisonous_potato":2,"stat.drop.astralsorcery.blocklens":1,"stat.pickup.skyresources.condenser":5,"stat.pickup.soot.stamp_nugget":1,"stat.mineBlock.fp.scanner_block":2,"stat.useItem.minecraft.cobblestone":163,"stat.drop.flexibletools.shovi":1,"stat.craftItem.exnihilocreatio.block_waterwheel":12,"stat.craftItem.primal.cauldron_lid":2,"stat.pickup.botania.blacklotus":5,"stat.craftItem.exnihilocreatio.block_sieve":46,"stat.pickup.environmentaltech.structure_frame_3":56,"stat.mineBlock.libvulpes.blockphantom":10,"stat.pickup.environmentaltech.structure_frame_2":88,"stat.craftItem.fp.opti_bench":1,"stat.pickup.minecraft.iron_pickaxe":3,"stat.pickup.environmentaltech.structure_frame_1":120,"stat.useItem.tconstruct.pickaxe":1067,"stat.mineBlock.survivalist.rack":2,"stat.craftItem.structuredcrafting.structured_crafter":8,"stat.pickup.minecraft.hopper":69,"stat.mineBlock.primal.blue_stone":28,"stat.mineBlock.fp.modul_2":3,"stat.useItem.xlfoodmod.baguette":7,"stat.mineBlock.fp.modul_1":8,"stat.useItem.buildcrafttransport.pipe_wood_fluid":2,"stat.drop.simplyjetpacks.itemjetpack":1,"stat.useItem.xlfoodmod.tomato":11,"stat.useItem.chisel.basalt2":3637,"stat.useItem.minecraft.wooden_door":3,"stat.craftItem.actuallyadditions.item_helm_crystal_green":4,"stat.craftItem.environmentaltech.connector":504,"stat.pickup.forestry.squeezer":3,"stat.craftItem.minecraft.paper":12,"stat.pickup.minecraft.red_flower":150,"stat.pickup.exnihilocreatio.block_sieve":13,"stat.pickup.immersiveengineering.connector":231,"stat.drop.botania.manaresource":1,"stat.pickup.refinedstorage.portable_grid":3,"stat.pickup.astralsorcery.blockblackmarble":103,"stat.drop.embers.ember_bore":1,"stat.pickup.primal.rush_tips_bloom":220,"stat.killEntity.FP-Crawler":9,"stat.mineBlock.roots.runestone":57,"stat.pickup.flexibletools.swordi":7,"stat.mineBlock.minecraft.yellow_flower":2,"stat.pickup.astralsorcery.itemcelestialcrystal":18,"stat.useItem.minecraft.concrete_powder":45,"stat.pickup.forestry.fermenter":2,"stat.pickup.minecraft.glowstone":3,"stat.craftItem.embers.stamper":2,"stat.useItem.openblocks.elevator":3,"stat.craftItem.minecraft.arrow":288,"stat.pickup.minecraft.sticky_piston":8,"stat.pickup.industrialforegoing.range_addon":1,"stat.pickup.embers.stamper":6,"stat.craftItem.fp.triebwerk":4,"stat.craftItem.buildcraftcore.wrench":2,"stat.pickup.roots.herblore_book":2,"stat.pickup.fp.block_breaker":4,"stat.craftItem.buildcraftsilicon.advanced_crafting_table":2,"stat.pickup.refinedstorage.solderer":4,"stat.pickup.fp.quantanium":211,"stat.useItem.minecraft.egg":332,"stat.useItem.primal.stone_gallagher":5,"stat.useItem.fp.color_plasma_on":17,"stat.pickup.embers.pipe":71,"stat.craftItem.minecraft.cooked_beef":23,"stat.mineBlock.minecraft.obsidian":164,"stat.craftItem.environmentaltech.interconnect":89,"stat.pickup.mist.rocks":5593,"stat.flyOneCm":15221133,"stat.pickup.minecraft.sandstone":22,"stat.useItem.survivalist.rock":129,"stat.pickup.minecraft.fish":598,"stat.craftItem.forestry.moistener":2,"stat.useItem.backpacks16840.backpack":29,"stat.mineBlock.extendedcrafting.table_basic":6,"stat.pickup.magneticraft.conveyor_belt":5,"stat.pickup.yabba.item_barrel":10,"stat.pickup.roots.fairy_dust":20,"stat.pickup.fp.dirt":1285,"stat.pickup.buildcraftcore.engine":54,"stat.craftItem.primal.flint_knapp":276,"stat.craftItem.embers.alchemy_pedestal":2,"stat.pickup.fp.neon_sand":850,"stat.pickup.minecraft.string":65,"stat.pickup.forestry.moistener":3,"stat.pickup.magneticraft.electric_furnace":2,"stat.pickup.waterstrainer.strainer_survivalist_reinforced":1,"stat.useItem.immersivetech.stone_decoration":17,"stat.useItem.embers.ember_emitter":4,"stat.craftItem.tconstruct.tooltables":28,"stat.pickup.flexibletools.tool_upgrade_skill":3,"stat.pickup.roots.firestarter":1,"stat.drop.immersiveengineering.connector":1,"stat.craftItem.embers.item_pipe":128,"stat.useItem.enderstorage.ender_storage":7,"stat.pickup.survivalist.jerky":2,"stat.pickup.primal.sarsen_stone":50,"stat.mineBlock.fp.block_breaker":4,"stat.craftItem.skyresources.casing":7,"stat.pickup.biomesoplenty.bamboo":16,"stat.pickup.fp.fuelcell":1,"stat.pickup.chisel.laboratory":36,"stat.mineBlock.forestry.squeezer":3,"stat.craftItem.immersiveengineering.wirecoil":1340,"stat.useItem.advancedrocketry.structuretower":25,"stat.mineBlock.fp.techtable":27,"stat.diveOneCm":129762,"stat.pickup.tconstruct.tooltables":10,"stat.pickup.survivalist.rock":6855,"stat.pickup.botania.grassseeds":31,"stat.mineBlock.environmentaltech.structure_frame_1":48,"stat.mineBlock.forestry.ash_block":192,"stat.craftItem.tconstruct.lumberaxe":1,"stat.mineBlock.bibliocraft.shelf":2,"stat.pickup.primal.adobebrick_wet":3,"stat.pickup.xnet.connector":2,"stat.pickup.xnet.controller":2,"stat.mineBlock.buildcraftsilicon.advanced_crafting_table":6,"stat.craftItem.thermalexpansion.machine":6,"stat.mineBlock.immersiveengineering.connector":187,"stat.craftItem.exnihilocreatio.block_crucible":10,"stat.jump":11084,"stat.useItem.minecraft.sand":242,"stat.pickup.astralsorcery.itemknowledgeshare":1,"stat.mineBlock.embers.alchemy_tablet":4,"stat.drop.biomesoplenty.mudball":1,"stat.pickup.buildcraftfactory.tank":28,"stat.mineBlock.embers.pipe":61,"stat.pickup.magneticraft.sluice_box":8,"stat.pickup.botania.runealtar":4,"stat.drop.thermalexpansion.augment":2,"stat.useItem.minecraft.glass":74,"stat.craftItem.refinedstorage.importer":1,"stat.mineBlock.primal.hardened_stone":1,"stat.mineBlock.fp.zentrifuge":3,"stat.useItem.immcraft.furnace":1,"stat.pickup.botania.doubleflower2":6,"stat.craftItem.buildcraftcore.engine":36,"stat.pickup.mist.acid_sand":1,"stat.pickup.botania.doubleflower1":1,"stat.pickup.primal.flint_knapp":168,"stat.pickup.advancedrocketry.launchpad":14,"stat.mineBlock.skyresources.casing":6,"stat.drop.tconstruct.slimesling":1,"stat.craftItem.skyresources.redsandstoneinfusionstone":24,"stat.cauldronUsed":14,"stat.pickup.minecraft.quartz_block":1,"stat.pickup.xlfoodmod.rice_seeds":3,"stat.pickup.mist.t_tree_branch":60,"stat.useItem.forge.bucketfilled":499,"stat.mineBlock.botania.alchemycatalyst":2,"stat.pickup.embers.aspectus_silver":1,"stat.useItem.immersiveengineering.metal_device0":1,"stat.useItem.immersiveengineering.metal_device1":1,"stat.mineBlock.exnihilocreatio.block_barrel1":2,"stat.killEntity.Silverfish":3,"stat.mineBlock.exnihilocreatio.block_barrel0":11,"stat.pickup.rftools.remote_storage":2,"stat.pickup.mist.acid_dirt_1":26,"stat.craftItem.minecraft.stone_slab":40,"stat.pickup.mist.acid_dirt_2":2,"stat.pickup.mist.acid_dirt_0":5,"stat.mineBlock.actuallyadditions.block_empowerer":1,"stat.animalsBred":2650,"stat.useItem.minecraft.chest":67,"stat.craftItem.survivalist.rock":4,"stat.mineBlock.skyresources.fluiddropper":3,"stat.craftItem.buildcrafttransport.pipe_cobble_fluid":1,"stat.pickup.chisel.factory":3,"stat.mineBlock.fp.dungeon_core":3,"stat.mineBlock.primal.hibachi":2,"stat.pickup.botania.cosmetic":1,"stat.pickup.biomesoplenty.leaves_1":4322,"stat.useItem.magneticraft.solar_panel":5,"stat.pickup.biomesoplenty.leaves_0":9,"stat.useItem.buildcrafttransport.pipe_clay_item":13,"stat.mineBlock.va.filteredhopper":1,"stat.useItem.fp.fuelcell":4,"stat.drop.minecraft.wooden_slab":1,"stat.craftItem.fp.telescope":1,"stat.useItem.forestry.loam":207,"stat.mineBlock.waystones.waystone":25,"stat.useItem.botania.livingrock":26,"stat.pickup.botania.floatingspecialflower":4,"stat.craftItem.fp.cristall":3393,"stat.pickup.roots.pereskia_bulb":144,"stat.craftItem.fp.plasma_generator_on":1,"stat.drop.minecraft.quartz_block":4,"stat.drop.minecraft.stone_axe":1,"stat.pickup.fp.itemerze":149,"stat.pickup.flexibletools.tool_upgrade_effect":1,"stat.craftItem.minecraft.compass":2,"stat.useItem.xlfoodmod.strawberry":11,"stat.pickup.embers.item_pump":49,"stat.mineBlock.storagedrawers.basicdrawers":26,"stat.useItem.primal.fish_puffer_dried":3,"stat.useItem.fp.brennstoff_generator":3,"stat.pickup.environmentaltech.laser_lens_crystal":1,"stat.pickup.minecraft.lapis_block":4,"stat.pickup.astralsorcery.itemconstellationpaper":2,"stat.useItem.chisel.technicalnew":98,"stat.useItem.astralsorcery.blockwell":6,"stat.pickup.embers.item_transfer":3,"stat.pickup.primal.flint_point":264,"stat.mineBlock.earthworks.block_wattle":42,"stat.craftItem.embers.item_transfer":4,"stat.pickup.minecraft.glass":40,"stat.pickup.tconstruct.slimesling":1,"stat.pickup.fp.itemfood":5,"stat.drop.roots.spellcraft_book":1,"stat.useItem.minecraft.water_bucket":161,"stat.pickup.roots.thatch":6,"stat.pickup.minecraft.hardened_clay":641,"stat.mineBlock.survivalist.chopping_block":5,"stat.useItem.storagedrawers.compdrawers":6,"stat.useItem.botania.grassseeds":14,"stat.craftItem.buildcraftfactory.autoworkbench_item":7,"stat.drop.minecraft.hardened_clay":117,"stat.mineBlock.openblocks.tank":14,"stat.mineBlock.appliedenergistics2.grindstone":1,"stat.useItem.minecraft.ender_pearl":1,"stat.pickup.waystones.warp_stone":1,"stat.pickup.embers.ashen_brick_slab":3,"stat.pickup.woot.stygianironplate":2,"stat.pickup.immersiveengineering.wirecoil":172,"stat.craftItem.fp.metal_gitter_pane":12,"stat.craftItem.minecraft.cooked_fish":29,"stat.craftItem.libvulpes.hatch":10,"stat.mineBlock.embers.alchemy_pedestal":5,"stat.craftItem.minecraft.blaze_powder":2,"stat.drop.astralsorcery.itemjournal":2,"stat.craftItem.biomesoplenty.mud_brick":16,"stat.useItem.minecraft.spawn_egg":2,"stat.craftItem.advancedrocketry.planetidchip":4,"stat.pickup.embers.block_furnace":7,"stat.drop.primal.adobebrick_mix":1,"stat.craftItem.botania.pavement4stairs":16,"stat.craftItem.fp.pipe":41,"stat.craftItem.minecraft.hardened_clay":96,"stat.craftItem.advancedrocketry.stationbuilder":1,"stat.drop.ceramics.clay_bucket":10,"stat.useItem.minecraft.oak_stairs":2,"stat.craftItem.yabba.item_barrel":2,"stat.craftItem.embers.mech_core":2,"stat.craftItem.refinedstorage.machine_casing":3,"stat.pickup.roots.spellcraft_book":1,"stat.useItem.survivalist.chopping_block":5,"stat.drop.exnihilocreatio.block_sieve":2,"stat.craftItem.survivalist.chopping_block":32,"stat.useItem.minecraft.redstone":35,"stat.mineBlock.botania.pavement":1,"stat.craftItem.jaff.tank":32,"stat.craftItem.advancedrocketry.satellitebuilder":1,"stat.mineBlock.industrialforegoing.mob_slaughter_factory":1,"stat.pickup.buildcrafttransport.pipe_cobble_item":57,"stat.pickup.rftools.screen":2,"stat.mineBlock.terraqueous.flowers_single":4,"stat.craftItem.chisel.laboratory":64,"stat.pickup.botania.pavement4stairs":3,"stat.craftItem.soot.stamp_nugget_raw":2,"stat.useItem.minecraft.hopper":10,"stat.mineBlock.extendedcrafting.table_elite":2,"stat.pickup.botania.overgrowthseed":2,"stat.drop.minecraft.string":40,"stat.pickup.roots.wildroot_item":134,"stat.pickup.minecraft.diamond_block":1,"stat.useItem.minecraft.shears":1,"stat.mineBlock.transprot.dispatcher":5,"stat.craftItem.primal.plant_cordage":588,"stat.drop.primal.flint_axe":1,"stat.craftItem.thermalexpansion.device":8,"stat.craftItem.immersiveengineering.wooden_device1":2,"stat.craftItem.immersiveengineering.wooden_device0":2,"stat.mineBlock.skyresources.combustioncollector":1,"stat.pickup.fp.opti_bench":3,"stat.craftItem.appliedenergistics2.material":2208,"stat.mineBlock.refinedstorage.controller":3,"stat.useItem.biomesoplenty.turnip":15,"stat.mineBlock.tconstruct.faucet":4,"stat.pickup.tconstruct.lumberaxe":1,"stat.useItem.minecraft.iron_hoe":79,"stat.drop.primal.rush_tips":1,"stat.mineBlock.primal.torch_wood":166,"stat.pickup.mist.sponge_meat":4,"stat.pickup.tconstruct.channel":24,"stat.useItem.transprot.linker":20,"stat.pickup.xlfoodmod.strawberry":7,"stat.craftItem.tconstruct.seared_tank":1,"stat.mineBlock.mist.acid_sand":1,"stat.useItem.minecraft.stone_sword":20,"stat.craftItem.buildcraftcore.gear_stone":14,"stat.craftItem.exnihilocreatio.block_auto_sifter":3,"stat.drop.terraqueous.multifood":1,"stat.mineBlock.rftools.modular_storage":2,"stat.drop.industrialforegoing.pink_slime":1,"stat.drop.minecraft.stick":5,"stat.craftItem.tconstruct.channel":3,"stat.useItem.fp.wandrope":13,"stat.pickup.terraqueous.multifood":4,"stat.pickup.magneticraft.solar_panel":9,"stat.craftItem.fp.grenade_launcher":1,"stat.pickup.botania.livingrock0wall":10,"stat.drop.ironchest.iron_chest":1,"stat.drop.biomesoplenty.coral":31,"stat.pickup.fp.eisenleiter":13,"stat.killEntity.LavaSlime":1,"stat.useItem.botania.specialflower":1,"stat.drop.immersiveengineering.tool":2,"stat.mineBlock.storagedrawers.compdrawers":6,"stat.mineBlock.fp.plasma_generator_on":1,"stat.useItem.astralsorcery.blocklens":8,"stat.pickup.minecraft.tallgrass":15,"stat.drop.botania.manatablet":36,"stat.drop.minecraft.lapis_block":8,"stat.useItem.chisel.hardenedclay":91,"stat.pickup.environmentaltech.pladium_crystal":448,"stat.useItem.forestry.ffarm":65,"stat.mineBlock.embers.ember_receiver":2,"stat.craftItem.minecraft.snow":7,"stat.useItem.biomesoplenty.leaves_1":30,"stat.pickup.xlfoodmod.taco_salad":2,"stat.craftItem.fp.forscher":1,"stat.craftItem.advancedrocketry.dataunit":4,"stat.craftItem.fp.assembly_table":1,"stat.craftItem.minecraft.cooked_chicken":6,"stat.useItem.teslacorelib.wrench":4,"stat.useItem.minecraft.stone_hoe":131,"stat.pickup.primal.diamond_point":74,"stat.craftItem.buildcraftsilicon.assembly_table":2,"stat.pickup.immersiveengineering.metal_device0":41,"stat.pickup.immersiveengineering.metal_device1":14,"stat.drop.botania.livingrock":39,"stat.pickup.biomesoplenty.turnip_seeds":10,"stat.craftItem.waterstrainer.strainer_survivalist_dense_solid":20,"stat.craftItem.refinedstorage.exporter":1,"stat.useItem.minecraft.beetroot":20,"stat.pickup.minecraft.chest":95,"stat.drop.foundry.machine":6,"stat.craftItem.earthworks.block_chalk":195,"stat.useItem.minecraft.repeater":8,"stat.pickup.biomesoplenty.turnip":4,"stat.mineBlock.embers.ember_bore":8,"stat.craftItem.biomesoplenty.mudball":16,"stat.mineBlock.fp.wandrope":170,"stat.pickup.exnihilocreatio.block_auto_sifter":7,"stat.useItem.fp.wr_receiver":5,"stat.useItem.advancedrocketry.rocketmotor":1,"stat.drop.buildcraftcore.engine":1,"stat.pickup.minecraft.enchanting_table":7,"stat.craftItem.fp.compactenergycell":1,"stat.craftItem.primal.flint_shovel":1,"stat.mineBlock.minecraft.magma":41,"stat.useItem.minecraft.stone_shovel":6428,"stat.pickup.appliedenergistics2.material":7039,"stat.pickup.compactmachines3.wallbreakable":32,"stat.drop.minecraft.wheat_seeds":9,"stat.craftItem.minecraft.wooden_slab":230,"stat.mineBlock.astralsorcery.blockaltar":5,"stat.craftItem.primal.adobebrick_mix":72,"stat.craftItem.vimmersion.hammer":2,"stat.pickup.fp.wr_transmitter":6,"stat.pickup.advancedrocketry.rocketbuilder":2,"stat.pickup.survivalist.rock_ore":383,"stat.pickup.skyresources.techitemcomponent":64,"stat.useItem.embers.item_pump":17,"stat.craftItem.minecraft.brick_block":2,"stat.craftItem.minecraft.stone_slab2":0,"stat.mineBlock.environmentaltech.laser_lens":3,"stat.useItem.roots.runestone":12,"stat.craftItem.waterstrainer.net":112,"stat.useItem.immersiveengineering.wirecoil":289,"stat.craftItem.minecraft.stone":411,"stat.mineBlock.minecraft.crafting_table":5,"stat.craftItem.tconstruct.clear_glass":122,"stat.mineBlock.environmentaltech.laser_lens_colored":3,"stat.craftItem.fp.energycell":5,"stat.mineBlock.skyresources.rockcrusher":3,"stat.useItem.minecraft.carrot":22,"stat.pickup.exnihilocreatio.block_waterwheel":12,"stat.pickup.thermalfoundation.armor.helmet_lead":3,"stat.pickup.flexibletools.tool_upgrade_support":7,"stat.useItem.buildcrafttransport.pipe_obsidian_item":1,"stat.pickup.minecraft.slime_ball":128,"stat.drop.minecraft.blaze_rod":1,"stat.pickup.earthworks.block_wattle":52,"stat.mineBlock.astralsorcery.blockcelestialcrystals":19,"stat.useItem.thermalfoundation.wrench":261,"stat.useItem.flexibletools.swordi":1044,"stat.pickup.fp.wandrope":173,"stat.mineBlock.buildcraftsilicon.assembly_table":6,"stat.useItem.immersiveengineering.metal_decoration2":4,"stat.useItem.immersiveengineering.metal_decoration1":2,"stat.pickup.astralsorcery.itemrockcrystalsimple":244,"stat.useItem.immersiveengineering.metal_decoration0":1,"stat.pickup.minecraft.brick":40,"stat.useItem.storagedrawers.basicdrawers":24,"stat.useItem.openblocks.tank":25,"stat.mineBlock.refinedstorage.disk_drive":3,"stat.pickup.deepresonance.resonating_ore":32,"stat.useItem.rftools.smartwrench":20,"stat.drop.mist.niobium_pickaxe":1,"stat.craftItem.fp.fish_block":2,"stat.useItem.minecraft.cooked_chicken":6,"stat.mineBlock.waterstrainer.strainer_base":25,"stat.pickup.minecraft.snow":4,"stat.pickup.botania.dreamwood":9,"stat.pickup.mist.stone_basic":29,"stat.pickup.primal.bear_fat":5,"stat.useItem.astralsorcery.blockcustomore":51,"stat.drop.skyresources.sandstoneinfusionstone":1,"stat.craftItem.buildcrafttransport.pipe_wood_item":72,"stat.pickup.minecraft.reeds":469,"stat.pickup.minecraft.prismarine_crystals":5,"stat.craftItem.earthworks.item_sand":260,"stat.useItem.minecraft.magma":4,"stat.pickup.thermalfoundation.storage_alloy":1,"stat.pickup.skyresources.combustioncollector":2,"stat.craftItem.minecraft.baked_potato":91,"stat.craftItem.minecraft.iron_sword":1,"stat.drop.embers.crystal_ember":1,"stat.craftItem.electrostatics.tree_tap":3,"stat.pickup.openblocks.auto_enchantment_table":5,"stat.pickup.fp.forscher":4,"stat.drop.appliedenergistics2.material":10,"stat.drop.biomesoplenty.terrestrial_artifact":7,"stat.pickup.embers.plate_dawnstone":28,"stat.useItem.immersiveengineering.sheetmetal":120,"stat.useItem.biomesoplenty.bamboo":6,"stat.mineBlock.chisel.basalt2":1908,"stat.pickup.terraqueous.item_main":5284,"stat.drop.minecraft.slime":1,"stat.drop.minecraft.emerald":30,"stat.drop.thermalfoundation.upgrade":1,"stat.mineBlock.fp.forscher":4,"stat.pickup.roots.wood_shears":1,"stat.pickup.primal.ferro_stone":41,"stat.craftItem.embers.alchemy_tablet":2,"stat.pickup.astralsorcery.itemcraftingcomponent":103,"stat.craftItem.fp.ind_neon_furn":4,"stat.useItem.sparkshammers.excavator_stone":1293,"stat.mineBlock.primal.logs_stripped":12,"stat.pickup.minecraft.water_bucket":1,"stat.drop.primal.flint_workblade":1,"stat.useItem.embers.caminite_lever":3,"stat.pickup.forestry.engine_biogas":1,"stat.craftItem.minecraft.coal_block":8,"stat.craftItem.fp.spaceship":349,"stat.useItem.mist.stone_basic":21,"stat.craftItem.exnihilocreatio.item_mesh":95,"stat.pickup.industrialforegoing.crop_sower":2,"stat.mineBlock.immcraft.sticks":12}