{"stat.mineBlock.forestry.wood_pile":1,"stat.pickup.minecraft.wooden_slab":1,"stat.leaveGame":13,"stat.mineBlock.tconstruct.channel":14,"stat.craftItem.minecraft.string":20,"stat.pickup.tconstruct.faucet":1,"stat.pickup.minecraft.rotten_flesh":50,"stat.pickup.waterstrainer.strainer_base":14,"stat.craftItem.minecraft.stone_axe":7,"stat.pickup.minecraft.bucket":1,"stat.useItem.botania.flower":5,"stat.mineBlock.minecraft.wooden_slab":1,"stat.craftItem.bibliocraft.shelf":1,"stat.pickup.xlfoodmod.strawberry_seeds":2,"stat.pickup.xlfoodmod.lettuce":3,"stat.craftItem.roots.runestone_brick":4,"stat.craftItem.forestry.fertilizer_bio":1,"stat.useItem.primal.barrel":7,"stat.pickup.primal.obsidian_plate":3,"stat.mineBlock.foundry.machine":8,"stat.pickup.minecraft.double_plant":20,"stat.craftItem.minecraft.bed":1,"stat.craftItem.minecraft.glass_pane":16,"stat.craftItem.buildcrafttransport.pipe_wood_fluid":2,"stat.useItem.roots.runestone_brick":2,"stat.pickup.thermalfoundation.material":32,"stat.furnaceInteraction":46,"stat.useItem.minecraft.pumpkin_seeds":2,"stat.mineBlock.botania.flower":2,"stat.pickup.jaff.tank":6,"stat.drop.minecraft.red_flower":3,"stat.useItem.waterstrainer.strainer_base":6,"stat.craftItem.primal.flint_workblade":1,"stat.pickup.botania.livingwood":16,"stat.pickup.tinkerskyblock.wooden_hopper":2,"stat.useItem.exnihilocreatio.item_seed_potato":1,"stat.drop.botania.dreamwood":1,"stat.mineBlock.minecraft.fence":3,"stat.useItem.minecraft.flint_and_steel":18,"stat.craftItem.primal.hardened_stone":19,"stat.useItem.botania.twigwand":2,"stat.useItem.minecraft.dye":57,"stat.craftItem.primal.brickform":5,"stat.pickup.minecraft.lever":8,"stat.deaths":2,"stat.pickup.roots.straw":96,"stat.pickup.xlfoodmod.raw_corn":2,"stat.craftItem.waterstrainer.strainer_survivalist_solid":5,"stat.useItem.survivalist.jerky":22,"stat.drop.minecraft.iron_ingot":1,"stat.drop.minecraft.torch":1,"stat.mineBlock.minecraft.tallgrass":7,"stat.chestOpened":558,"stat.drop.waterstrainer.strainer_survivalist_dense":2,"stat.craftItem.embers.ashen_stone":16,"stat.drop.primal.flint_knapp":12,"stat.pickup.immersiveengineering.material":79,"stat.craftItem.modularmachinery.blockcasing":9,"stat.mineBlock.biomesoplenty.bamboo":1,"stat.pickup.oreberries.tin_oreberry":3,"stat.craftItem.primal.flint_axe":8,"stat.useItem.actuallyadditions.item_food":6,"stat.useItem.embers.ashen_stone":15,"stat.pickup.primal.brickform":11,"stat.pickup.chisel.basalt2":28,"stat.crouchOneCm":11788,"stat.mineBlock.minecraft.chest":1,"stat.pickup.earthworks.block_concrete":34,"stat.useItem.immcraft.chest":4,"stat.craftItem.foundry.componentblock":1,"stat.drop.immcraft.furnace":2,"stat.craftingTableInteraction":164,"stat.drop.roots.firestarter":1,"stat.useItem.primal.torch_wood":22,"stat.craftItem.buildcrafttransport.waterproof":2,"stat.mineBlock.biomesoplenty.mud":1,"stat.pickup.xlfoodmod.tomato":3,"stat.pickup.minecraft.dye":1,"stat.pickup.minecraft.planks":529,"stat.pickup.minecraft.wheat_seeds":9,"stat.mineBlock.botania.altgrass":262,"stat.mineBlock.minecraft.dirt":132,"stat.pickup.biomesoplenty.persimmon":11,"stat.pickup.skyresources.alchemyitemcomponent":10,"stat.flowerPotted":1,"stat.pickup.immersiveengineering.seed":31,"stat.mineBlock.biomesoplenty.leaves_1":883,"stat.craftItem.biomesoplenty.plant_0":1,"stat.craftItem.primal.barrel":14,"stat.useItem.minecraft.cobblestone":18,"stat.mineBlock.minecraft.double_plant":6,"stat.pickup.tconstruct.pickaxe":2,"stat.drop.forestry.loam":1,"stat.useItem.actuallyadditions.item_canola_seed":1,"stat.useItem.tconstruct.pickaxe":108,"stat.mineBlock.biomesoplenty.sapling_0":5,"stat.pickup.roots.wood_knife":1,"stat.useItem.modularmachinery.blockinputbus":2,"stat.useItem.astralsorcery.itemarchitectwand":9,"stat.pickup.forestry.ash":100,"stat.mineBlock.primal.brickform":11,"stat.drop.minecraft.fish":1,"stat.craftItem.waterstrainer.strainer_base":4,"stat.craftItem.minecraft.bucket":1,"stat.craftItem.minecraft.dirt":452,"stat.pickup.magneticraft.stone_hammer":1,"stat.useItem.buildcrafttransport.pipe_wood_fluid":1,"stat.pickup.minecraft.stone_sword":1,"stat.mineBlock.minecraft.log":645,"stat.craftItem.minecraft.wooden_door":3,"stat.drop.forestry.portable_alyzer":2,"stat.useItem.chisel.basalt2":28,"stat.useItem.minecraft.wooden_door":1,"stat.useItem.biomesoplenty.dirt":1,"stat.pickup.biomesoplenty.dirt":5,"stat.pickup.minecraft.red_flower":60,"stat.mineBlock.magneticraft.sluice_box":1,"stat.craftItem.minecraft.cobblestone":129,"stat.pickup.primal.rush_tips_bloom":29,"stat.mineBlock.minecraft.cobblestone":73,"stat.mineBlock.roots.runestone":54,"stat.mineBlock.minecraft.pumpkin":4,"stat.pickup.roots.pereskia_blossom":38,"stat.pickup.minecraft.flint":87,"stat.drop.thermalfoundation.material":9,"stat.pickup.buildcrafttransport.pipe_clay_item":3,"stat.pickup.minecraft.flower_pot":2,"stat.craftItem.minecraft.wool":3,"stat.craftItem.modularmachinery.blockinputbus":4,"stat.craftItem.primal.flint_saw":1,"stat.mineBlock.botania.runealtar":1,"stat.useItem.minecraft.stone_slab2":337,"stat.useItem.jaff.tank":20,"stat.pickup.roots.herblore_book":2,"stat.craftItem.minecraft.furnace":2,"stat.craftItem.biomesoplenty.mud":200,"stat.useItem.primal.stone_gallagher":5,"stat.pickup.earthworks.block_chalk":4,"stat.pickup.primal.torch_wood":134,"stat.flyOneCm":12569,"stat.pickup.actuallyadditions.item_booklet":1,"stat.useItem.survivalist.rock":7,"stat.pickup.minecraft.fish":41,"stat.useItem.biomesoplenty.mudball":98,"stat.pickup.roots.bonfire":2,"stat.pickup.foundry.castingtable":12,"stat.timeSinceDeath":1270879,"stat.useItem.minecraft.wooden_slab":1,"stat.mineBlock.botania.livingwood":17,"stat.pickup.buildcraftcore.engine":7,"stat.pickup.xlfoodmod.cucumber_seeds":3,"stat.pickup.immcraft.furnace":1,"stat.pickup.roots.runestone":54,"stat.useItem.buildcrafttransport.pipe_iron_item":1,"stat.craftItem.earthworks.item_chalk":8,"stat.drop.botania.livingwood":16,"stat.craftItem.tconstruct.tooltables":2,"stat.sprintOneCm":679372,"stat.pickup.forestry.portable_alyzer":2,"stat.pickup.roots.firestarter":1,"stat.useItem.carryon.tile_item":13,"stat.pickup.survivalist.jerky":2,"stat.pickup.modularmachinery.itemblueprint":1,"stat.waystones:waystonesActivated":10,"stat.pickup.biomesoplenty.bamboo":16,"stat.pickup.waterstrainer.efficiency_meter":1,"stat.craftItem.minecraft.wooden_pressure_plate":2,"stat.craftItem.minecraft.dye":4,"stat.diveOneCm":62120,"stat.pickup.minecraft.wheat":6,"stat.craftItem.minecraft.sandstone":17,"stat.pickup.survivalist.rock":256,"stat.pickup.botania.grassseeds":27,"stat.mineBlock.forestry.ash_block":48,"stat.craftItem.tconstruct.lumberaxe":1,"stat.pickup.primal.adobebrick_wet":3,"stat.mineBlock.botania.spreader":1,"stat.pickup.primal.bark_oak":35,"stat.jump":986,"stat.useItem.minecraft.sand":10,"stat.pickup.immcraft.rock":31,"stat.pickup.minecraft.coal":608,"stat.pickup.minecraft.iron_ingot":13,"stat.craftItem.minecraft.lever":5,"stat.pickup.thermalfoundation.armor.legs_lead":1,"stat.pickup.magneticraft.sluice_box":1,"stat.pickup.botania.runealtar":1,"stat.pickup.minecraft.dirt":405,"stat.craftItem.modularmachinery.blockcontroller":2,"stat.drop.ceramics.unfired_clay":1,"stat.drop.tconstruct.clear_glass":1,"stat.mineBlock.primal.hardened_stone":1,"stat.pickup.primal.plant_fiber":560,"stat.drop.magneticraft.stone_hammer":1,"stat.pickup.buildcrafttransport.pipe_iron_item":1,"stat.craftItem.immcraft.rock":9,"stat.damageTaken":-2147478258,"stat.useItem.immcraft.furnace":1,"stat.craftItem.buildcraftcore.engine":1,"stat.mineBlock.minecraft.red_flower":1,"stat.pickup.primal.flint_knapp":76,"stat.pickup.biomesoplenty.ash_block":49,"stat.useItem.roots.wildroot_item":2,"stat.craftItem.buildcraftcore.gear_wood":4,"stat.pickup.xlfoodmod.rice_seeds":3,"stat.pickup.exnihilocreatio.item_seed_potato":1,"stat.pickup.botania.spreader":1,"stat.pickup.minecraft.potato":1,"stat.drop.botania.petal":8,"stat.drop.survivalist.rock":3,"stat.useItem.primal.flint_shovel":320,"stat.craftItem.primal.plant_fiber":68,"stat.useItem.minecraft.chest":1,"stat.drop.minecraft.wheat":5,"stat.drop.primal.hardened_stone":1,"stat.pickup.buildcrafttransport.pipe_wood_item":6,"stat.useItem.minecraft.lava_bucket":2,"stat.pickup.tconstruct.clear_glass":11,"stat.pickup.biomesoplenty.leaves_1":1105,"stat.pickup.biomesoplenty.leaves_0":9,"stat.useItem.buildcrafttransport.pipe_clay_item":4,"stat.drop.minecraft.wooden_slab":1,"stat.mineBlock.forestry.loam":47,"stat.pickup.biomesoplenty.gem":3,"stat.useItem.forestry.loam":69,"stat.pickup.roots.terra_moss_spore":64,"stat.pickup.roots.chiseled_runestone":18,"stat.drop.primal.adobebrick_dry":1,"stat.mineBlock.waystones.waystone":6,"stat.mobKills":3,"stat.drop.botania.lexicon":1,"stat.pickup.botania.floatingspecialflower":1,"stat.drop.biomesoplenty.dirt":4,"stat.pickup.minecraft.beetroot_seeds":7,"stat.pickup.roots.pereskia_bulb":57,"stat.mineBlock.immcraft.chest":12,"stat.useItem.primal.fish_puffer_dried":3,"stat.useItem.biomesoplenty.ash_block":998,"stat.pickup.primal.adobebrick_mix":1,"stat.useItem.minecraft.planks":4,"stat.drop.tconstruct.pickaxe":1,"stat.pickup.primal.flint_point":7,"stat.mineBlock.roots.chiseled_runestone":18,"stat.mineBlock.earthworks.block_wattle":42,"stat.craftItem.ceramics.clay_shears":1,"stat.useItem.primal.rush_seeds":53,"stat.drop.roots.spellcraft_book":1,"stat.useItem.minecraft.water_bucket":3,"stat.pickup.roots.thatch":1,"stat.pickup.minecraft.sand":8,"stat.useItem.botania.grassseeds":11,"stat.pickup.earthworks.block_cob":27,"stat.mineBlock.biomesoplenty.ash_block":3613,"stat.mineBlock.minecraft.sand":8,"stat.hopperInspected":26,"stat.craftItem.biomesoplenty.mud_brick":16,"stat.mineBlock.terraqueous.doodads":109,"stat.useItem.tconstruct.channel":8,"stat.drop.primal.adobebrick_mix":1,"stat.mineBlock.biomesoplenty.dirt":1,"stat.pickup.exnihilocreatio.block_barrel0":1,"stat.drop.ceramics.clay_bucket":4,"stat.pickup.roots.moonglow_leaf":19,"stat.pickup.xlfoodmod.lettuce_seeds":3,"stat.craftItem.thermalfoundation.material":9,"stat.pickup.roots.spellcraft_book":1,"stat.useItem.survivalist.chopping_block":3,"stat.pickup.roots.terra_moss_ball":32,"stat.craftItem.survivalist.chopping_block":24,"stat.drop.biomesoplenty.ash":62,"stat.pickup.botania.spark":4,"stat.pickup.primal.adobebrick_dry":22,"stat.craftItem.jaff.tank":32,"stat.drop.primal.flint_shears":1,"stat.useItem.earthworks.block_wattle":39,"stat.useItem.buildcrafttransport.pipe_cobble_item":2,"stat.pickup.buildcrafttransport.pipe_cobble_item":2,"stat.useItem.tconstruct.scythe":641,"stat.drop.earthworks.item_sand":2,"stat.useItem.botania.petal":3,"stat.drop.biomesoplenty.leaves_0":9,"stat.drop.biomesoplenty.leaves_1":3,"stat.craftItem.minecraft.sand":377,"stat.useItem.immersiveengineering.seed":1,"stat.drop.waterstrainer.strainer_base":1,"stat.craftItem.primal.wood_pin":12,"stat.useItem.buildcrafttransport.pipe_wood_item":6,"stat.pickup.botania.overgrowthseed":1,"stat.craftItem.tconstruct.scythe":1,"stat.useItem.xlfoodmod.tomato_seeds":1,"stat.useItem.forestry.wood_pile":55,"stat.pickup.xlfoodmod.pepper_seeds":2,"stat.playOneMinute":1911735,"stat.pickup.roots.wildroot_item":62,"stat.mineBlock.botania.forestdrum":1,"stat.drop.chisel.basalt2":9,"stat.drop.minecraft.chest":1,"stat.pickup.waterstrainer.strainer_survivalist_dense":2,"stat.useItem.jaff.fish_bucket_cod":1,"stat.craftItem.primal.plant_cordage":204,"stat.mineBlock.botania.specialflower":1,"stat.drop.primal.flint_axe":1,"stat.pickup.minecraft.pumpkin":4,"stat.craftItem.immcraft.furnace":2,"stat.drop.minecraft.flint":1,"stat.useItem.biomesoplenty.turnip":15,"stat.mineBlock.earthworks.block_cob":30,"stat.mineBlock.tconstruct.faucet":1,"stat.fallOneCm":41775,"stat.useItem.primal.fish_cod_dried":9,"stat.useItem.primal.flint_axe":337,"stat.drop.minecraft.dye":15,"stat.useItem.modularmachinery.itemblueprint":10,"stat.pickup.minecraft.melon_seeds":2,"stat.craftItem.earthworks.block_adobe":6,"stat.mineBlock.minecraft.lever":6,"stat.craftItem.primal.flint_shears":1,"stat.useItem.earthworks.block_concrete":31,"stat.craftItem.modularmachinery.blockoutputbus":2,"stat.mineBlock.primal.torch_wood":27,"stat.pickup.earthworks.item_sand":1,"stat.useItem.biomesoplenty.mud":1,"stat.craftItem.tconstruct.materials":18,"stat.pickup.primal.rush_stems":42,"stat.pickup.tconstruct.channel":15,"stat.craftItem.waterstrainer.strainer_survivalist_dense":21,"stat.mineBlock.buildcrafttransport.pipe_diamond_fluid":9,"stat.useItem.minecraft.stone_pickaxe":50,"stat.craftItem.tconstruct.seared_tank":1,"stat.pickup.waystones.waystone":6,"stat.useItem.minecraft.stone_sword":1,"stat.pickup.primal.logs_split_oak":45,"stat.drop.terraqueous.multifood":1,"stat.drop.primal.plant_fiber":3,"stat.pickup.botania.specialflower":2,"stat.drop.minecraft.stick":5,"stat.pickup.minecraft.flint_and_steel":1,"stat.useItem.roots.wood_hammer":9,"stat.craftItem.tconstruct.channel":3,"stat.useItem.minecraft.torch":56,"stat.pickup.minecraft.iron_nugget":2,"stat.drop.primal.logs_split_oak":1,"stat.useItem.minecraft.log":45,"stat.pickup.minecraft.crafting_table":2,"stat.useItem.primal.brickform":2,"stat.useItem.exnihilocreatio.item_seed_cactus":1,"stat.pickup.biomesoplenty.coral":4,"stat.craftItem.minecraft.crafting_table":6,"stat.drop.biomesoplenty.coral":31,"stat.pickup.primal.flint_axe":1,"stat.drop.survivalist.rock_ore":7,"stat.craftItem.primal.thatching_wet":10,"stat.pickup.minecraft.log":627,"stat.pickup.immcraft.chest":15,"stat.useItem.biomesoplenty.persimmon":3,"stat.drop.minecraft.planks":4,"stat.craftItem.foundry.component":8,"stat.pickup.minecraft.wooden_door":2,"stat.useItem.roots.chiseled_runestone":5,"stat.pickup.minecraft.beetroot":8,"stat.pickup.roots.aubergine_seeds":69,"stat.pickup.primal.rush_tips":53,"stat.drop.immersiveengineering.material":1,"stat.useItem.biomesoplenty.leaves_1":28,"stat.pickup.roots.aubergine_item":24,"stat.useItem.minecraft.wooden_pressure_plate":1,"stat.useItem.primal.fish_clown_dried":1,"stat.sneakTime":27458,"stat.pickup.biomesoplenty.turnip_seeds":6,"stat.craftItem.waterstrainer.strainer_survivalist_dense_solid":3,"stat.drop.minecraft.bucket":1,"stat.pickup.minecraft.yellow_flower":8,"stat.useItem.minecraft.beetroot":18,"stat.pickup.minecraft.chest":1,"stat.drop.foundry.machine":1,"stat.pickup.minecraft.bone":60,"stat.craftItem.buildcrafttransport.pipe_cobble_item":16,"stat.craftItem.ceramics.unfired_clay":5,"stat.craftItem.earthworks.block_chalk":32,"stat.pickup.biomesoplenty.turnip":4,"stat.craftItem.waterstrainer.strainer_survivalist":12,"stat.craftItem.botania.petal":8,"stat.craftItem.biomesoplenty.mudball":12,"stat.craftItem.foundry.machine":1,"stat.swimOneCm":20535,"stat.climbOneCm":131313,"stat.mineBlock.botania.floatingspecialflower":1,"stat.pickup.roots.moontinged_seed":36,"stat.craftItem.appliedenergistics2.crank":1,"stat.useItem.minecraft.dirt":715,"stat.useItem.primal.flint_hatchet":31,"stat.drop.oreberries.iron_oreberry":1,"stat.useItem.tconstruct.lumberaxe":173,"stat.pickup.botania.forestdrum":1,"stat.craftItem.minecraft.trapdoor":10,"stat.craftItem.primal.flint_shovel":1,"stat.craftItem.minecraft.stone_pickaxe":1,"stat.craftItem.buildcrafttransport.pipe_clay_item":8,"stat.pickup.minecraft.cobblestone":3,"stat.mineBlock.roots.bonfire":2,"stat.mineBlock.buildcraftcore.engine":7,"stat.pickup.thermalfoundation.armor.plate_lead":1,"stat.useItem.minecraft.stone_shovel":3239,"stat.pickup.exnihilocreatio.item_seed_cactus":1,"stat.pickup.minecraft.clay":83,"stat.drop.minecraft.wheat_seeds":1,"stat.craftItem.minecraft.wooden_slab":64,"stat.pickup.minecraft.cactus":11,"stat.craftItem.modularmachinery.blockfluidinputhatch":1,"stat.ae2.TurnedCranks":291,"stat.craftItem.actuallyadditions.item_food":7,"stat.craftItem.primal.adobebrick_mix":32,"stat.craftItem.forestry.wood_pile":67,"stat.drop.minecraft.log":16,"stat.pickup.actuallyadditions.item_rice_seed":4,"stat.drop.minecraft.coal":37,"stat.pickup.primal.flint_shears":1,"stat.pickup.minecraft.trapdoor":1,"stat.pickup.forestry.honey_drop":1,"stat.craftItem.tconstruct.soil":18,"stat.mineBlock.tinkerskyblock.wooden_hopper":2,"stat.pickup.primal.rock_stone":7,"stat.pickup.xlfoodmod.corn_seeds":2,"stat.craftItem.minecraft.stone_slab2":0,"stat.pickup.botania.petal":3,"stat.drop.exnihilocreatio.block_barrel0":2,"stat.useItem.primal.flint_workblade":79,"stat.drop.roots.ritual_book":1,"stat.pickup.biomesoplenty.ash":14088,"stat.useItem.roots.runestone":12,"stat.craftItem.waterstrainer.net":44,"stat.pickup.exnihilocreatio.item_material":2,"stat.craftItem.minecraft.stone":39,"stat.mineBlock.minecraft.crafting_table":2,"stat.useItem.astralsorcery.itemexchangewand":9,"stat.craftItem.minecraft.clay_ball":232,"stat.pickup.botania.flower":2,"stat.mineBlock.minecraft.planks":6,"stat.pickup.thermalfoundation.armor.helmet_lead":1,"stat.drop":430,"stat.pickup.foundry.machine":8,"stat.pickup.earthworks.block_wattle":42,"stat.craftItem.primal.stone_gallagher":1,"stat.mineBlock.earthworks.block_concrete":34,"stat.craftItem.minecraft.piston":1,"stat.craftItem.buildcrafttransport.pipe_iron_item":8,"stat.mineBlock.roots.thatch":1,"stat.pickup.foundry.mold":13,"stat.craftItem.biomesoplenty.ash_block":3414,"stat.drop.tconstruct.channel":1,"stat.craftItem.survivalist.rack":2,"stat.useItem.immcraft.rock":1,"stat.pickup.minecraft.fence":2,"stat.pickup.forestry.wood_pile":1,"stat.useItem.tconstruct.tooltables":1,"stat.useItem.minecraft.stone_axe":195,"stat.mineBlock.waterstrainer.strainer_base":13,"stat.pickup.botania.dreamwood":1,"stat.mineBlock.immcraft.rock":21,"stat.pickup.primal.obsidian_shard":15,"stat.pickup.xlfoodmod.tomato_seeds":7,"stat.craftItem.minecraft.iron_bars":32,"stat.drop.skyresources.sandstoneinfusionstone":1,"stat.useItem.jaff.fish_bucket_pufferfish":1,"stat.craftItem.buildcrafttransport.pipe_wood_item":8,"stat.drop.primal.obsidian_plate":3,"stat.useItem.xlfoodmod.lettuce":3,"stat.drop.biomesoplenty.ash_block":88,"stat.damageDealt":175,"stat.craftItem.minecraft.glass":32,"stat.craftItem.minecraft.bowl":4,"stat.sleepInBed":5,"stat.useItem.exnihilocreatio.item_seed_sugarcane":1,"stat.mineBlock.jaff.tank":6,"stat.pickup.actuallyadditions.item_canola_seed":1,"stat.craftItem.skyresources.sandstoneinfusionstone":10,"stat.useItem.minecraft.crafting_table":1,"stat.craftItem.minecraft.gravel":308,"stat.craftItem.buildcraftfactory.pump":1,"stat.pickup.primal.hardened_stone":1,"stat.craftItem.tinkerskyblock.wooden_hopper":4,"stat.craftItem.minecraft.stone_shovel":27,"stat.walkOneCm":4485207,"stat.pickup.ceramics.clay_bucket":20,"stat.pickup.minecraft.stick":276,"stat.craftItem.exnihilocreatio.item_material":4,"stat.pickup.thermalfoundation.armor.boots_lead":1,"stat.useItem.primal.fish_salmon_dried":11,"stat.useItem.jaff.fish_bucket_clownfish":1,"stat.pickup.biomesoplenty.sapling_0":115,"stat.pickup.forestry.loam":47,"stat.useItem.biomesoplenty.bamboo":6,"stat.mineBlock.chisel.basalt2":67,"stat.craftItem.immcraft.chest":9,"stat.pickup.primal.rush_seeds":37,"stat.drop.modularmachinery.itemblueprint":1,"stat.drop.survivalist.jerky":3,"stat.pickup.biomesoplenty.mudball":20,"stat.pickup.minecraft.stone":58,"stat.pickup.primal.flint_shovel":1,"stat.craftItem.magneticraft.sluice_box":1,"stat.useItem.minecraft.cactus":4,"stat.useItem.jaff.fish_bucket_salmon":1,"stat.pickup.forestry.apatite":5,"stat.drop.forestry.apatite":29,"stat.mineBlock.minecraft.cactus":14,"stat.mineBlock.foundry.castingtable":11,"stat.useItem.primal.flint_pickaxe":131,"stat.useItem.biomesoplenty.sapling_0":105,"stat.craftItem.exnihilocreatio.block_barrel0":3,"stat.mineBlock.primal.logs_stripped":12,"stat.craftItem.exnihilocreatio.item_mesh":1,"stat.mineBlock.immcraft.sticks":1}